[
  {
    "localId": 934401196,
    "title": "Nier Automata Nintendo Switch folia",
    "thumbnail": "https://ireland.apollo.olxcdn.com/v1/files/ktf1p42kjoq73-PL/image;s=200x0;q=50",
    "url": "https://www.olx.pl/d/oferta/nier-automata-nintendo-switch-folia-CID99-ID11eEr2.html",
    "pricePLN": "144,99 zł",
    "city": "Warszawa, Żoliborz",
    "type": "BUY_NOW",
    "productType": "NEW",
    "date": "30.7.2024 00:17",
    "timestamp": 1722298620000
  },
  {
    "localId": 934389948,
    "title": "Gra LEGO GWIEZDNE WOJNY Saga Skywalkerów Nintendo Switch PL polska wer",
    "thumbnail": "https://ireland.apollo.olxcdn.com/v1/files/hq3nhkhep4um1-PL/image;s=200x0;q=50",
    "url": "https://www.olx.pl/d/oferta/gra-lego-gwiezdne-wojny-saga-skywalkerow-nintendo-switch-pl-polska-wer-CID99-ID11eBwC.html",
    "pricePLN": "85,99 zł",
    "city": "Bolesławiec",
    "type": "BUY_NOW",
    "productType": "USED",
    "date": "29 lipca 2024",
    "timestamp": null
  },
  {
    "localId": 934389477,
    "title": "Metroid Dread na Nintendo Switch - nieoryginalne pudełko",
    "thumbnail": "https://ireland.apollo.olxcdn.com/v1/files/alurjb0fweqw-PL/image;s=200x0;q=50",
    "url": "https://www.olx.pl/d/oferta/metroid-dread-na-nintendo-switch-nieoryginalne-pudelko-CID99-ID11eBo1.html",
    "pricePLN": "89 zł",
    "city": "Warszawa, Ursynów",
    "type": "BUY_NOW",
    "productType": "USED",
    "date": "29 lipca 2024",
    "timestamp": null
  },
  {
    "localId": 934388900,
    "title": "Gra Minecraft Nintendo Switch PL dystrybucja Super Mario Mash-up",
    "thumbnail": "https://ireland.apollo.olxcdn.com/v1/files/rx3m2vkvlze5-PL/image;s=200x0;q=50",
    "url": "https://www.olx.pl/d/oferta/gra-minecraft-nintendo-switch-pl-dystrybucja-super-mario-mash-up-CID99-ID11eBeI.html",
    "pricePLN": "79,99 zł",
    "city": "Bolesławiec",
    "type": "BUY_NOW",
    "productType": "USED",
    "date": "29 lipca 2024",
    "timestamp": null
  },
  {
    "localId": 934388135,
    "title": "Gra Super Mario ODYSSEY Nintendo Switch idealny stan",
    "thumbnail": "https://ireland.apollo.olxcdn.com/v1/files/0qn7plqkpzwr3-PL/image;s=200x0;q=50",
    "url": "https://www.olx.pl/d/oferta/gra-super-mario-odyssey-nintendo-switch-idealny-stan-CID99-ID11eB2n.html",
    "pricePLN": "139,99 zł",
    "city": "Bolesławiec",
    "type": "BUY_NOW",
    "productType": "USED",
    "date": "29 lipca 2024",
    "timestamp": null
  },
  {
    "localId": 934387764,
    "title": "Gra The Legend Of Zelda Breath Of The Wild BOTW Nintendo Switch PL dys",
    "thumbnail": "https://www.olx.pl/app/static/media/no_thumbnail.c222b0530.svg",
    "url": "https://www.olx.pl/d/oferta/gra-the-legend-of-zelda-breath-of-the-wild-botw-nintendo-switch-pl-dys-CID99-ID11eAVo.html",
    "pricePLN": "149,99 zł",
    "city": "Bolesławiec",
    "type": "BUY_NOW",
    "productType": "USED",
    "date": "29 lipca 2024",
    "timestamp": null
  },
  {
    "localId": 934384380,
    "title": "Gra Nintendo Stern pinball arcade",
    "thumbnail": "https://www.olx.pl/app/static/media/no_thumbnail.c222b0530.svg",
    "url": "https://www.olx.pl/d/oferta/gra-nintendo-stern-pinball-arcade-CID99-ID11eA3O.html",
    "pricePLN": "25 zł",
    "city": "Chorzów",
    "type": "BUY_NOW",
    "productType": "NEW",
    "date": "29 lipca 2024",
    "timestamp": null
  },
  {
    "localId": 934384249,
    "title": "Gra Nintendo farm expert",
    "thumbnail": "https://www.olx.pl/app/static/media/no_thumbnail.c222b0530.svg",
    "url": "https://www.olx.pl/d/oferta/gra-nintendo-farm-expert-CID99-ID11eA1H.html",
    "pricePLN": "25 zł",
    "city": "Chorzów",
    "type": "BUY_NOW",
    "productType": "NEW",
    "date": "29 lipca 2024",
    "timestamp": null
  },
  {
    "localId": 934383311,
    "title": "The Legend of Zelda: Tears of the Kingdom",
    "thumbnail": "https://www.olx.pl/app/static/media/no_thumbnail.c222b0530.svg",
    "url": "https://www.olx.pl/d/oferta/the-legend-of-zelda-tears-of-the-kingdom-CID99-ID11ezMz.html",
    "pricePLN": "160 zł\ndo negocjacji",
    "city": "Kostomłoty Drugie",
    "type": "BUY_NOW",
    "productType": "USED",
    "date": "29 lipca 2024",
    "timestamp": null
  },
  {
    "localId": 934380032,
    "title": "Super Mario 3D All Stars nintendo switch",
    "thumbnail": "https://www.olx.pl/app/static/media/no_thumbnail.c222b0530.svg",
    "url": "https://www.olx.pl/d/oferta/super-mario-3d-all-stars-nintendo-switch-CID99-ID11eyWG.html",
    "pricePLN": "250 zł",
    "city": "Dąbrówka",
    "type": "BUY_NOW",
    "productType": "USED",
    "date": "29 lipca 2024",
    "timestamp": null
  },
  {
    "localId": 934376084,
    "title": "The Legend Of Zelda Breath Of The Wild",
    "thumbnail": "https://www.olx.pl/app/static/media/no_thumbnail.c222b0530.svg",
    "url": "https://www.olx.pl/d/oferta/the-legend-of-zelda-breath-of-the-wild-CID99-ID11exU0.html",
    "pricePLN": "140 zł",
    "city": "Gdańsk, Chełm z dzielnicą Gdańsk Południe",
    "type": "BUY_NOW",
    "productType": "USED",
    "date": "29 lipca 2024",
    "timestamp": null
  },
  {
    "localId": 934375927,
    "title": "Metroid Dread Nintendo Switch",
    "thumbnail": "https://www.olx.pl/app/static/media/no_thumbnail.c222b0530.svg",
    "url": "https://www.olx.pl/d/oferta/metroid-dread-nintendo-switch-CID99-ID11exRt.html",
    "pricePLN": "130 zł",
    "city": "Myślenice",
    "type": "BUY_NOW",
    "productType": "USED",
    "date": "29 lipca 2024",
    "timestamp": null
  },
  {
    "localId": 934375614,
    "title": "Blasphemous 2 switch nowa",
    "thumbnail": "https://www.olx.pl/app/static/media/no_thumbnail.c222b0530.svg",
    "url": "https://www.olx.pl/d/oferta/blasphemous-2-switch-nowa-CID99-ID11exMq.html",
    "pricePLN": "95 zł",
    "city": "Płock",
    "type": "BUY_NOW",
    "productType": "NEW",
    "date": "29 lipca 2024",
    "timestamp": null
  },
  {
    "localId": 928726133,
    "title": "The Legend Of Zelda The Tears Of The Kingdom",
    "thumbnail": "https://www.olx.pl/app/static/media/no_thumbnail.c222b0530.svg",
    "url": "https://www.olx.pl/d/oferta/the-legend-of-zelda-the-tears-of-the-kingdom-CID99-ID10QQ5L.html",
    "pricePLN": "160 zł",
    "city": "Warszawa, Mokotów",
    "type": "BUY_NOW",
    "productType": "USED",
    "date": "29 lipca 2024",
    "timestamp": null
  },
  {
    "localId": 934365478,
    "title": "Ace Combat 7 Skies Unknown Deluxe Edition Nintendo Switch",
    "thumbnail": "https://www.olx.pl/app/static/media/no_thumbnail.c222b0530.svg",
    "url": "https://www.olx.pl/d/oferta/ace-combat-7-skies-unknown-deluxe-edition-nintendo-switch-CID99-ID11ew8V.html",
    "pricePLN": "135 zł",
    "city": "Lublin",
    "type": "BUY_NOW",
    "productType": "USED",
    "date": "29 lipca 2024",
    "timestamp": null
  },
  {
    "localId": 934362028,
    "title": "Mario Rabbids sparks of hope Nintendo switch",
    "thumbnail": "https://www.olx.pl/app/static/media/no_thumbnail.c222b0530.svg",
    "url": "https://www.olx.pl/d/oferta/mario-rabbids-sparks-of-hope-nintendo-switch-CID99-ID11eufi.html",
    "pricePLN": "50 zł",
    "city": "Warszawa, Mokotów",
    "type": "BUY_NOW",
    "productType": "USED",
    "date": "29 lipca 2024",
    "timestamp": null
  },
  {
    "localId": 934353445,
    "title": "Mario Rabidds Nintendo Switch",
    "thumbnail": "https://www.olx.pl/app/static/media/no_thumbnail.c222b0530.svg",
    "url": "https://www.olx.pl/d/oferta/mario-rabidds-nintendo-switch-CID99-ID11es0R.html",
    "pricePLN": "49 zł",
    "city": "Sosnowiec",
    "type": "BUY_NOW",
    "productType": "USED",
    "date": "29 lipca 2024",
    "timestamp": null
  },
  {
    "localId": 934351626,
    "title": "Stojak na Kartridże Nintendo Switch",
    "thumbnail": "https://www.olx.pl/app/static/media/no_thumbnail.c222b0530.svg",
    "url": "https://www.olx.pl/d/oferta/stojak-na-kartridze-nintendo-switch-CID99-ID11erxv.html",
    "pricePLN": "55 zł\ndo negocjacji",
    "city": "Bydgoszcz",
    "type": "BUY_NOW",
    "productType": "NEW",
    "date": "29 lipca 2024",
    "timestamp": null
  },
  {
    "localId": 928725691,
    "title": "Pokemon Let’s Go Eeve",
    "thumbnail": "https://www.olx.pl/app/static/media/no_thumbnail.c222b0530.svg",
    "url": "https://www.olx.pl/d/oferta/pokemon-lets-go-eeve-CID99-ID10QPYD.html",
    "pricePLN": "160 zł",
    "city": "Warszawa, Mokotów",
    "type": "BUY_NOW",
    "productType": "USED",
    "date": "29 lipca 2024",
    "timestamp": null
  },
  {
    "localId": 934344050,
    "title": "Mario + Rabbids Sparks of Hope oraz Super Mario 3D World + Bowsers Fur",
    "thumbnail": "https://www.olx.pl/app/static/media/no_thumbnail.c222b0530.svg",
    "url": "https://www.olx.pl/d/oferta/mario-rabbids-sparks-of-hope-oraz-super-mario-3d-world-bowsers-fur-CID99-ID11epzk.html",
    "pricePLN": "162 zł",
    "city": "Kraśnik",
    "type": "BUY_NOW",
    "productType": "USED",
    "date": "29 lipca 2024",
    "timestamp": null
  },
  {
    "localId": 934343046,
    "title": "Gra Super Mario Odyssey Nintendo Switch NS",
    "thumbnail": "https://www.olx.pl/app/static/media/no_thumbnail.c222b0530.svg",
    "url": "https://www.olx.pl/d/oferta/gra-super-mario-odyssey-nintendo-switch-ns-CID99-ID11epj8.html",
    "pricePLN": "119,90 zł",
    "city": "Wawrów",
    "type": "BUY_NOW",
    "productType": "USED",
    "date": "29 lipca 2024",
    "timestamp": null
  },
  {
    "localId": 934335998,
    "title": "Nintendo switch lite",
    "thumbnail": "https://www.olx.pl/app/static/media/no_thumbnail.c222b0530.svg",
    "url": "https://www.olx.pl/d/oferta/nintendo-switch-lite-CID99-ID11ents.html",
    "pricePLN": "850 zł\ndo negocjacji",
    "city": "Lubsza",
    "type": "BUY_NOW",
    "productType": "USED",
    "date": "29 lipca 2024",
    "timestamp": null
  },
  {
    "localId": 928162984,
    "title": "Crash bandicoot 4",
    "thumbnail": "https://www.olx.pl/app/static/media/no_thumbnail.c222b0530.svg",
    "url": "https://www.olx.pl/d/oferta/crash-bandicoot-4-CID99-ID10OtAI.html",
    "pricePLN": "105 zł",
    "city": "Łowicz",
    "type": "BUY_NOW",
    "productType": "USED",
    "date": "29 lipca 2024",
    "timestamp": null
  },
  {
    "localId": 934335398,
    "title": "Prince of Persja -The Lost Crown Nintendo Switch",
    "thumbnail": "https://www.olx.pl/app/static/media/no_thumbnail.c222b0530.svg",
    "url": "https://www.olx.pl/d/oferta/prince-of-persja-the-lost-crown-nintendo-switch-CID99-ID11enjM.html",
    "pricePLN": "107 zł\ndo negocjacji",
    "city": "Kraków, Bieńczyce",
    "type": "BUY_NOW",
    "productType": "USED",
    "date": "29 lipca 2024",
    "timestamp": null
  },
  {
    "localId": 934331159,
    "title": "FIFA 2020 Nintendo Switch PL polska",
    "thumbnail": "https://www.olx.pl/app/static/media/no_thumbnail.c222b0530.svg",
    "url": "https://www.olx.pl/d/oferta/fifa-2020-nintendo-switch-pl-polska-CID99-ID11emdp.html",
    "pricePLN": "75 zł",
    "city": "Chorzów",
    "type": "BUY_NOW",
    "productType": "USED",
    "date": "29 lipca 2024",
    "timestamp": null
  },
  {
    "localId": 934330019,
    "title": "Bayonetta 2 Nintendo Switch",
    "thumbnail": "https://www.olx.pl/app/static/media/no_thumbnail.c222b0530.svg",
    "url": "https://www.olx.pl/d/oferta/bayonetta-2-nintendo-switch-CID99-ID11elW1.html",
    "pricePLN": "70 zł",
    "city": "Hoczew",
    "type": "BUY_NOW",
    "productType": "USED",
    "date": "29 lipca 2024",
    "timestamp": null
  },
  {
    "localId": 934329586,
    "title": "Splatoon 2 Nintendo Switch",
    "thumbnail": "https://www.olx.pl/app/static/media/no_thumbnail.c222b0530.svg",
    "url": "https://www.olx.pl/d/oferta/splatoon-2-nintendo-switch-CID99-ID11elO2.html",
    "pricePLN": "70 zł",
    "city": "Hoczew",
    "type": "BUY_NOW",
    "productType": "USED",
    "date": "29 lipca 2024",
    "timestamp": null
  },
  {
    "localId": 934327512,
    "title": "Super Maio Party switch",
    "thumbnail": "https://www.olx.pl/app/static/media/no_thumbnail.c222b0530.svg",
    "url": "https://www.olx.pl/d/oferta/super-maio-party-switch-CID99-ID11elgA.html",
    "pricePLN": "169 zł",
    "city": "Tarnowskie Góry",
    "type": "BUY_NOW",
    "productType": "USED",
    "date": "29 lipca 2024",
    "timestamp": null
  },
  {
    "localId": 934326989,
    "title": "Super Mario Bros: Wonder Gra NINTENDO SWITCH",
    "thumbnail": "https://www.olx.pl/app/static/media/no_thumbnail.c222b0530.svg",
    "url": "https://www.olx.pl/d/oferta/super-mario-bros-wonder-gra-nintendo-switch-CID99-ID11el89.html",
    "pricePLN": "140 zł",
    "city": "Ozorków",
    "type": "BUY_NOW",
    "productType": "USED",
    "date": "29 lipca 2024",
    "timestamp": null
  },
  {
    "localId": 934326699,
    "title": "Burnout Paradise remastered switch",
    "thumbnail": "https://www.olx.pl/app/static/media/no_thumbnail.c222b0530.svg",
    "url": "https://www.olx.pl/d/oferta/burnout-paradise-remastered-switch-CID99-ID11el3t.html",
    "pricePLN": "95 zł\ndo negocjacji",
    "city": "Katowice, Janów",
    "type": "BUY_NOW",
    "productType": "USED",
    "date": "Nikiszowiec",
    "timestamp": null
  },
  {
    "localId": 934315812,
    "title": "Will a wonderful world Nintendo switch",
    "thumbnail": "https://www.olx.pl/app/static/media/no_thumbnail.c222b0530.svg",
    "url": "https://www.olx.pl/d/oferta/will-a-wonderful-world-nintendo-switch-CID99-ID11eidS.html",
    "pricePLN": "169 zł",
    "city": "Kraków, Krowodrza",
    "type": "BUY_NOW",
    "productType": "USED",
    "date": "29 lipca 2024",
    "timestamp": null
  },
  {
    "localId": 934314782,
    "title": "Doki doki literature club plus Nintendo switch",
    "thumbnail": "https://www.olx.pl/app/static/media/no_thumbnail.c222b0530.svg",
    "url": "https://www.olx.pl/d/oferta/doki-doki-literature-club-plus-nintendo-switch-CID99-ID11ehXg.html",
    "pricePLN": "119 zł",
    "city": "Kraków, Krowodrza",
    "type": "BUY_NOW",
    "productType": "USED",
    "date": "29 lipca 2024",
    "timestamp": null
  },
  {
    "localId": 934314455,
    "title": "Nintendo Switch gry",
    "thumbnail": "https://www.olx.pl/app/static/media/no_thumbnail.c222b0530.svg",
    "url": "https://www.olx.pl/d/oferta/nintendo-switch-gry-CID99-ID11ehRZ.html",
    "pricePLN": "280 zł",
    "city": "Nowe Miasto Lubawskie",
    "type": "BUY_NOW",
    "productType": "USED",
    "date": "29 lipca 2024",
    "timestamp": null
  },
  {
    "localId": 934314303,
    "title": "A space for the unbound Nintendo switch",
    "thumbnail": "https://www.olx.pl/app/static/media/no_thumbnail.c222b0530.svg",
    "url": "https://www.olx.pl/d/oferta/a-space-for-the-unbound-nintendo-switch-CID99-ID11ehPx.html",
    "pricePLN": "119 zł",
    "city": "Kraków, Krowodrza",
    "type": "BUY_NOW",
    "productType": "USED",
    "date": "29 lipca 2024",
    "timestamp": null
  },
  {
    "localId": 934312280,
    "title": "Grisaia Phantom trigger 01 to 05",
    "thumbnail": "https://www.olx.pl/app/static/media/no_thumbnail.c222b0530.svg",
    "url": "https://www.olx.pl/d/oferta/grisaia-phantom-trigger-01-to-05-CID99-ID11ehiU.html",
    "pricePLN": "279 zł",
    "city": "Kraków, Krowodrza",
    "type": "BUY_NOW",
    "productType": "USED",
    "date": "29 lipca 2024",
    "timestamp": null
  },
  {
    "localId": 934311701,
    "title": "The elder scrolls V Skyrim Nintendo switch",
    "thumbnail": "https://www.olx.pl/app/static/media/no_thumbnail.c222b0530.svg",
    "url": "https://www.olx.pl/d/oferta/the-elder-scrolls-v-skyrim-nintendo-switch-CID99-ID11eh9z.html",
    "pricePLN": "145 zł",
    "city": "Kraków, Krowodrza",
    "type": "BUY_NOW",
    "productType": "USED",
    "date": "29 lipca 2024",
    "timestamp": null
  },
  {
    "localId": 934307355,
    "title": "Gra Prince of Persia The Lost Crown Nintendo Switch",
    "thumbnail": "https://www.olx.pl/app/static/media/no_thumbnail.c222b0530.svg",
    "url": "https://www.olx.pl/d/oferta/gra-prince-of-persia-the-lost-crown-nintendo-switch-CID99-ID11eg1t.html",
    "pricePLN": "100 zł",
    "city": "Ostrołęka",
    "type": "BUY_NOW",
    "productType": "USED",
    "date": "29 lipca 2024",
    "timestamp": null
  },
  {
    "localId": 934292737,
    "title": "Going Under (Nintendo Switch)",
    "thumbnail": "https://www.olx.pl/app/static/media/no_thumbnail.c222b0530.svg",
    "url": "https://www.olx.pl/d/oferta/going-under-nintendo-switch-CID99-ID11ecdH.html",
    "pricePLN": "160 zł",
    "city": "Gdańsk, Wrzeszcz",
    "type": "BUY_NOW",
    "productType": "USED",
    "date": "29 lipca 2024",
    "timestamp": null
  },
  {
    "localId": 934306638,
    "title": "Dark Souls remastered nintendo switch",
    "thumbnail": "https://www.olx.pl/app/static/media/no_thumbnail.c222b0530.svg",
    "url": "https://www.olx.pl/d/oferta/dark-souls-remastered-nintendo-switch-CID99-ID11efPU.html",
    "pricePLN": "100 zł",
    "city": "Szczecin, Zdroje",
    "type": "BUY_NOW",
    "productType": "USED",
    "date": "29 lipca 2024",
    "timestamp": null
  },
  {
    "localId": 934305727,
    "title": "Animal Crossing nintendo switch",
    "thumbnail": "https://www.olx.pl/app/static/media/no_thumbnail.c222b0530.svg",
    "url": "https://www.olx.pl/d/oferta/animal-crossing-nintendo-switch-CID99-ID11efBd.html",
    "pricePLN": "120 zł",
    "city": "Szczecin, Zdroje",
    "type": "BUY_NOW",
    "productType": "NEW",
    "date": "29 lipca 2024",
    "timestamp": null
  }
]