[
  {
    "localId": 949842171,
    "title": "Kao The Kangaroo PL Nintendo Switch - Rybnik Play_gamE",
    "thumbnail": "https://ireland.apollo.olxcdn.com/v1/files/8r6uhv7rp7e81-PL/image;s=200x0;q=50",
    "url": "https://www.olx.pl/d/oferta/kao-the-kangaroo-pl-nintendo-switch-rybnik-play-game-CID99-ID12hrl1.html",
    "pricePLN": "89,99 zł",
    "city": "Rybnik",
    "type": "BUY_NOW",
    "date": "4.11.2024 13:23",
    "timestamp": 1730726580000
  },
  {
    "localId": 949819962,
    "title": "Splatoon 2 Nintendo Switch, BDB, CentrumGrania",
    "thumbnail": "https://ireland.apollo.olxcdn.com/v1/files/sibmiuknsa7s-PL/image;s=200x0;q=50",
    "url": "https://www.olx.pl/d/oferta/splatoon-2-nintendo-switch-bdb-centrumgrania-CID99-ID12hlyO.html",
    "pricePLN": "119 zł",
    "city": "Lublin",
    "type": "BUY_NOW",
    "date": "4.11.2024 13:00",
    "timestamp": 1730725200000
  },
  {
    "localId": 957195309,
    "title": "Gra Labo Vehicle Kit 3 Nintendo Switch",
    "thumbnail": "https://ireland.apollo.olxcdn.com/v1/files/897jf8ql1ao83-PL/image;s=200x0;q=50",
    "url": "https://www.olx.pl/d/oferta/gra-labo-vehicle-kit-3-nintendo-switch-CID99-ID12Mie1.html",
    "pricePLN": "50 zł",
    "city": "Tarnowskie Góry",
    "type": "BUY_NOW",
    "date": "4.11.2024 12:54",
    "timestamp": 1730724840000
  },
  {
    "localId": 957188727,
    "title": "Bayonetta 3 na Nintendo Switch - używana, stan idealny",
    "thumbnail": "https://ireland.apollo.olxcdn.com/v1/files/ndmc73iwd9jt3-PL/image;r=90;s=200x0;q=50",
    "url": "https://www.olx.pl/d/oferta/bayonetta-3-na-nintendo-switch-uzywana-stan-idealny-CID99-ID12MgwR.html",
    "pricePLN": "89 zł",
    "city": "Solec Kujawski",
    "type": "BUY_NOW",
    "date": "4.11.2024 12:32",
    "timestamp": 1730723520000
  },
  {
    "localId": 957181996,
    "title": "Triangle strategy",
    "thumbnail": "https://ireland.apollo.olxcdn.com/v1/files/1cd89z8xo73b3-PL/image;s=200x0;q=50",
    "url": "https://www.olx.pl/d/oferta/triangle-strategy-CID99-ID12MeLi.html",
    "pricePLN": "130 zł",
    "city": "Szczecin, Centrum",
    "type": "BUY_NOW",
    "date": "4.11.2024 12:08",
    "timestamp": 1730722080000
  },
  {
    "localId": 942779156,
    "title": "The Walking Dead Nintendo Switch",
    "thumbnail": "https://www.olx.pl/app/static/media/no_thumbnail.c222b0530.svg",
    "url": "https://www.olx.pl/d/oferta/the-walking-dead-nintendo-switch-CID99-ID11NNWq.html",
    "pricePLN": "80 zł",
    "city": "Chocianów",
    "type": "BUY_NOW",
    "date": "4.11.2024 12:03",
    "timestamp": 1730721780000
  },
  {
    "localId": 942778894,
    "title": "The Raven Remastered Nintendo Switch",
    "thumbnail": "https://www.olx.pl/app/static/media/no_thumbnail.c222b0530.svg",
    "url": "https://www.olx.pl/d/oferta/the-raven-remastered-nintendo-switch-CID99-ID11NNRc.html",
    "pricePLN": "70 zł",
    "city": "Chocianów",
    "type": "BUY_NOW",
    "date": "4.11.2024 12:01",
    "timestamp": 1730721660000
  },
  {
    "localId": 936011078,
    "title": "Call of Cthulhu Switch gra Napisy PL",
    "thumbnail": "https://www.olx.pl/app/static/media/no_thumbnail.c222b0530.svg",
    "url": "https://www.olx.pl/d/oferta/call-of-cthulhu-switch-gra-napisy-pl-CID99-ID11lpeS.html",
    "pricePLN": "89 zł",
    "city": "Opole",
    "type": "BUY_NOW",
    "date": "4.11.2024 11:57",
    "timestamp": 1730721420000
  },
  {
    "localId": 936010414,
    "title": "Planescape Torment + Icewind Dale [Wydanie PL] - Nintendo Switch",
    "thumbnail": "https://www.olx.pl/app/static/media/no_thumbnail.c222b0530.svg",
    "url": "https://www.olx.pl/d/oferta/planescape-torment-icewind-dale-wydanie-pl-nintendo-switch-CID99-ID11lp4a.html",
    "pricePLN": "150 zł\ndo negocjacji",
    "city": "Sosnowiec",
    "type": "BUY_NOW",
    "date": "4.11.2024 11:54",
    "timestamp": 1730721240000
  },
  {
    "localId": 936009972,
    "title": "F.I.S.T. Forged In Shadow Torch [NTSC-J] - Nintendo Switch",
    "thumbnail": "https://www.olx.pl/app/static/media/no_thumbnail.c222b0530.svg",
    "url": "https://www.olx.pl/d/oferta/f-i-s-t-forged-in-shadow-torch-ntsc-j-nintendo-switch-CID99-ID11loX2.html",
    "pricePLN": "200 zł\ndo negocjacji",
    "city": "Sosnowiec",
    "type": "BUY_NOW",
    "date": "4.11.2024 11:53",
    "timestamp": 1730721180000
  },
  {
    "localId": 939380915,
    "title": "Super Smash Bros Ultimate Nintendo Switch",
    "thumbnail": "https://www.olx.pl/app/static/media/no_thumbnail.c222b0530.svg",
    "url": "https://www.olx.pl/d/oferta/super-smash-bros-ultimate-nintendo-switch-CID99-ID11zxT5.html",
    "pricePLN": "200 zł",
    "city": "Pruszków",
    "type": "BUY_NOW",
    "date": "4.11.2024 11:48",
    "timestamp": 1730720880000
  },
  {
    "localId": 957173092,
    "title": "The Legend Of Zelda Tears Of The Kingdom Nintendo Switch",
    "thumbnail": "https://www.olx.pl/app/static/media/no_thumbnail.c222b0530.svg",
    "url": "https://www.olx.pl/d/oferta/the-legend-of-zelda-tears-of-the-kingdom-nintendo-switch-CID99-ID12McrG.html",
    "pricePLN": "155 zł\ndo negocjacji",
    "city": "Warszawa, Żoliborz",
    "type": "BUY_NOW",
    "date": "4.11.2024 11:42",
    "timestamp": 1730720520000
  },
  {
    "localId": 936006514,
    "title": "Little nightmares 2 Nintendo switch",
    "thumbnail": "https://www.olx.pl/app/static/media/no_thumbnail.c222b0530.svg",
    "url": "https://www.olx.pl/d/oferta/little-nightmares-2-nintendo-switch-CID99-ID11lo3g.html",
    "pricePLN": "105 zł\ndo negocjacji",
    "city": "Polkowice",
    "type": "BUY_NOW",
    "date": "4.11.2024 11:40",
    "timestamp": 1730720400000
  },
  {
    "localId": 936006262,
    "title": "Dying light Nintendo switch",
    "thumbnail": "https://www.olx.pl/app/static/media/no_thumbnail.c222b0530.svg",
    "url": "https://www.olx.pl/d/oferta/dying-light-nintendo-switch-CID99-ID11lnZc.html",
    "pricePLN": "200 zł",
    "city": "Polkowice",
    "type": "BUY_NOW",
    "date": "4.11.2024 11:38",
    "timestamp": 1730720280000
  },
  {
    "localId": 949636448,
    "title": "The Legends Of Zelda Tears Of The Kingdom",
    "thumbnail": "https://www.olx.pl/app/static/media/no_thumbnail.c222b0530.svg",
    "url": "https://www.olx.pl/d/oferta/the-legends-of-zelda-tears-of-the-kingdom-CID99-ID12gzOU.html",
    "pricePLN": "190 zł\ndo negocjacji",
    "city": "Skawina",
    "type": "BUY_NOW",
    "date": "4.11.2024 11:38",
    "timestamp": 1730720280000
  },
  {
    "localId": 936005731,
    "title": "Devil may cry triple pack Nintendo switch",
    "thumbnail": "https://www.olx.pl/app/static/media/no_thumbnail.c222b0530.svg",
    "url": "https://www.olx.pl/d/oferta/devil-may-cry-triple-pack-nintendo-switch-CID99-ID11lnQD.html",
    "pricePLN": "250 zł",
    "city": "Polkowice",
    "type": "BUY_NOW",
    "date": "4.11.2024 11:37",
    "timestamp": 1730720220000
  },
  {
    "localId": 949812148,
    "title": "Super Mario Bros Wonder Switch",
    "thumbnail": "https://www.olx.pl/app/static/media/no_thumbnail.c222b0530.svg",
    "url": "https://www.olx.pl/d/oferta/super-mario-bros-wonder-switch-CID99-ID12hjvM.html",
    "pricePLN": "170 zł",
    "city": "Bielsko",
    "type": "BUY_NOW",
    "date": "Biała",
    "timestamp": null
  },
  {
    "localId": 957165269,
    "title": "Mario Rabbids sparks of hope Nintendo switch",
    "thumbnail": "https://www.olx.pl/app/static/media/no_thumbnail.c222b0530.svg",
    "url": "https://www.olx.pl/d/oferta/mario-rabbids-sparks-of-hope-nintendo-switch-CID99-ID12Mapw.html",
    "pricePLN": "50 zł",
    "city": "Pruszków",
    "type": "BUY_NOW",
    "date": "4.11.2024 11:19",
    "timestamp": 1730719140000
  },
  {
    "localId": 957164810,
    "title": "Princess peach showtime.",
    "thumbnail": "https://www.olx.pl/app/static/media/no_thumbnail.c222b0530.svg",
    "url": "https://www.olx.pl/d/oferta/princess-peach-showtime-CID99-ID12Mai6.html",
    "pricePLN": "110 zł",
    "city": "Pruszków",
    "type": "BUY_NOW",
    "date": "4.11.2024 11:18",
    "timestamp": 1730719080000
  },
  {
    "localId": 949808809,
    "title": "Elderand Nintendo SWITCH - NOWA, Skup/Sprzedaż",
    "thumbnail": "https://www.olx.pl/app/static/media/no_thumbnail.c222b0530.svg",
    "url": "https://www.olx.pl/d/oferta/elderand-nintendo-switch-nowa-skup-sprzedaz-CID99-ID12hiEW.html",
    "pricePLN": "89 zł",
    "city": "Bydgoszcz",
    "type": "BUY_NOW",
    "date": "4.11.2024 11:09",
    "timestamp": 1730718540000
  },
  {
    "localId": 957161256,
    "title": "Fire Emblem Three Houses gra Nintendo Switch",
    "thumbnail": "https://www.olx.pl/app/static/media/no_thumbnail.c222b0530.svg",
    "url": "https://www.olx.pl/d/oferta/fire-emblem-three-houses-gra-nintendo-switch-CID99-ID12M9mM.html",
    "pricePLN": "160 zł",
    "city": "Ożarów Mazowiecki",
    "type": "BUY_NOW",
    "date": "4.11.2024 11:07",
    "timestamp": 1730718420000
  },
  {
    "localId": 929676784,
    "title": "Gra pokemon nintendo switch",
    "thumbnail": "https://www.olx.pl/app/static/media/no_thumbnail.c222b0530.svg",
    "url": "https://www.olx.pl/d/oferta/gra-pokemon-nintendo-switch-CID99-ID10UPoQ.html",
    "pricePLN": "130 zł",
    "city": "Dzierżoniów",
    "type": "BUY_NOW",
    "date": "4.11.2024 11:02",
    "timestamp": 1730718120000
  },
  {
    "localId": 957158142,
    "title": "gra The Legend Of Zelda: Tears of the Kingdom Nintendo Switch",
    "thumbnail": "https://www.olx.pl/app/static/media/no_thumbnail.c222b0530.svg",
    "url": "https://www.olx.pl/d/oferta/gra-the-legend-of-zelda-tears-of-the-kingdom-nintendo-switch-CID99-ID12M8yy.html",
    "pricePLN": "180 zł",
    "city": "Łódź, Górna",
    "type": "BUY_NOW",
    "date": "4.11.2024 10:57",
    "timestamp": 1730717820000
  },
  {
    "localId": 949805122,
    "title": "Mario vs. Donkey Kong Gra NINTENDO SWITCH",
    "thumbnail": "https://www.olx.pl/app/static/media/no_thumbnail.c222b0530.svg",
    "url": "https://www.olx.pl/d/oferta/mario-vs-donkey-kong-gra-nintendo-switch-CID99-ID12hhHs.html",
    "pricePLN": "140 zł",
    "city": "Pruszcz Gdański",
    "type": "BUY_NOW",
    "date": "4.11.2024 10:55",
    "timestamp": 1730717700000
  },
  {
    "localId": 957157239,
    "title": "Ds lite i Pokemon Black",
    "thumbnail": "https://www.olx.pl/app/static/media/no_thumbnail.c222b0530.svg",
    "url": "https://www.olx.pl/d/oferta/ds-lite-i-pokemon-black-CID99-ID12M8jZ.html",
    "pricePLN": "630 zł",
    "city": "Kielce",
    "type": "BUY_NOW",
    "date": "4.11.2024 10:54",
    "timestamp": 1730717640000
  },
  {
    "localId": 957157322,
    "title": "One Piece Pirate Warriors 4 Nintendo Switch",
    "thumbnail": "https://www.olx.pl/app/static/media/no_thumbnail.c222b0530.svg",
    "url": "https://www.olx.pl/d/oferta/one-piece-pirate-warriors-4-nintendo-switch-CID99-ID12M8lk.html",
    "pricePLN": "120 zł",
    "city": "Limanowa",
    "type": "BUY_NOW",
    "date": "4.11.2024 10:54",
    "timestamp": 1730717640000
  },
  {
    "localId": 957155427,
    "title": "Kingdom Come Deliverance - Nintendo Switch",
    "thumbnail": "https://www.olx.pl/app/static/media/no_thumbnail.c222b0530.svg",
    "url": "https://www.olx.pl/d/oferta/kingdom-come-deliverance-nintendo-switch-CID99-ID12M7QL.html",
    "pricePLN": "160 zł",
    "city": "Kąty Wrocławskie",
    "type": "BUY_NOW",
    "date": "4.11.2024 10:48",
    "timestamp": 1730717280000
  },
  {
    "localId": 957155423,
    "title": "Minecraft Dungeons Ultimate Edition Nintendo Switch",
    "thumbnail": "https://www.olx.pl/app/static/media/no_thumbnail.c222b0530.svg",
    "url": "https://www.olx.pl/d/oferta/minecraft-dungeons-ultimate-edition-nintendo-switch-CID99-ID12M7QH.html",
    "pricePLN": "100 zł",
    "city": "Limanowa",
    "type": "BUY_NOW",
    "date": "4.11.2024 10:48",
    "timestamp": 1730717280000
  },
  {
    "localId": 957154357,
    "title": "Dredge Deluxe edition (switch - kartridż)",
    "thumbnail": "https://www.olx.pl/app/static/media/no_thumbnail.c222b0530.svg",
    "url": "https://www.olx.pl/d/oferta/dredge-deluxe-edition-switch-kartridz-CID99-ID12M7zw.html",
    "pricePLN": "105 zł",
    "city": "Szczecin, Niebuszewo",
    "type": "BUY_NOW",
    "date": "4.11.2024 10:45",
    "timestamp": 1730717100000
  },
  {
    "localId": 957154151,
    "title": "Super Mario RPG Nintendo Switch",
    "thumbnail": "https://www.olx.pl/app/static/media/no_thumbnail.c222b0530.svg",
    "url": "https://www.olx.pl/d/oferta/super-mario-rpg-nintendo-switch-CID99-ID12M7vb.html",
    "pricePLN": "80 zł\ndo negocjacji",
    "city": "Limanowa",
    "type": "BUY_NOW",
    "date": "4.11.2024 10:44",
    "timestamp": 1730717040000
  },
  {
    "localId": 957150172,
    "title": "Oddworld Collection; 3 gry na Switch'a",
    "thumbnail": "https://www.olx.pl/app/static/media/no_thumbnail.c222b0530.svg",
    "url": "https://www.olx.pl/d/oferta/oddworld-collection-3-gry-na-switcha-CID99-ID12M6u0.html",
    "pricePLN": "139 zł",
    "city": "Szczecin, Niebuszewo",
    "type": "BUY_NOW",
    "date": "4.11.2024 10:33",
    "timestamp": 1730716380000
  },
  {
    "localId": 957148559,
    "title": "Gra Pokemon legends arceus",
    "thumbnail": "https://www.olx.pl/app/static/media/no_thumbnail.c222b0530.svg",
    "url": "https://www.olx.pl/d/oferta/gra-pokemon-legends-arceus-CID99-ID12M63Z.html",
    "pricePLN": "155 zł",
    "city": "Koszalin",
    "type": "BUY_NOW",
    "date": "4.11.2024 10:29",
    "timestamp": 1730716140000
  },
  {
    "localId": 957148306,
    "title": "Prince of Persia The Lost Crown PL NS Nintendo Switch",
    "thumbnail": "https://www.olx.pl/app/static/media/no_thumbnail.c222b0530.svg",
    "url": "https://www.olx.pl/d/oferta/prince-of-persia-the-lost-crown-pl-ns-nintendo-switch-CID99-ID12M5ZU.html",
    "pricePLN": "90 zł",
    "city": "Białystok, Antoniuk",
    "type": "BUY_NOW",
    "date": "4.11.2024 10:28",
    "timestamp": 1730716080000
  },
  {
    "localId": 935984821,
    "title": "LEGO Przygoda 2 Nintendo Switch (nowa) wersja polska / możliwa zamiana",
    "thumbnail": "https://www.olx.pl/app/static/media/no_thumbnail.c222b0530.svg",
    "url": "https://www.olx.pl/d/oferta/lego-przygoda-2-nintendo-switch-nowa-wersja-polska-mozliwa-zamiana-CID99-ID11lipn.html",
    "pricePLN": "105 zł",
    "city": "Warszawa, Ursus",
    "type": "BUY_NOW",
    "date": "4.11.2024 10:27",
    "timestamp": 1730716020000
  },
  {
    "localId": 957145148,
    "title": "Pokemon Legends Arceus",
    "thumbnail": "https://www.olx.pl/app/static/media/no_thumbnail.c222b0530.svg",
    "url": "https://www.olx.pl/d/oferta/pokemon-legends-arceus-CID99-ID12M5aY.html",
    "pricePLN": "170 zł",
    "city": "Piła",
    "type": "BUY_NOW",
    "date": "4.11.2024 10:19",
    "timestamp": 1730715540000
  },
  {
    "localId": 957144519,
    "title": "Super Mario Bros Wonder - Jak Nowa - Na Prezent – Nintendo Switch",
    "thumbnail": "https://www.olx.pl/app/static/media/no_thumbnail.c222b0530.svg",
    "url": "https://www.olx.pl/d/oferta/super-mario-bros-wonder-jak-nowa-na-prezent-nintendo-switch-CID99-ID12M50P.html",
    "pricePLN": "150 zł",
    "city": "Zielona Góra",
    "type": "BUY_NOW",
    "date": "4.11.2024 10:17",
    "timestamp": 1730715420000
  },
  {
    "localId": 957143866,
    "title": "FC 25 Nintendo igla",
    "thumbnail": "https://www.olx.pl/app/static/media/no_thumbnail.c222b0530.svg",
    "url": "https://www.olx.pl/d/oferta/fc-25-nintendo-igla-CID99-ID12M4Qi.html",
    "pricePLN": "170 zł",
    "city": "Krosno",
    "type": "BUY_NOW",
    "date": "4.11.2024 10:15",
    "timestamp": 1730715300000
  },
  {
    "localId": 949793658,
    "title": "Nintendo Mario Rabbids Sparks Of Hope",
    "thumbnail": "https://www.olx.pl/app/static/media/no_thumbnail.c222b0530.svg",
    "url": "https://www.olx.pl/d/oferta/nintendo-mario-rabbids-sparks-of-hope-CID99-ID12heIy.html",
    "pricePLN": "75 zł",
    "city": "Gdańsk, Przymorze Małe",
    "type": "BUY_NOW",
    "date": "4.11.2024 10:12",
    "timestamp": 1730715120000
  },
  {
    "localId": 935979260,
    "title": "Railway Empire Nintendo Switch Edition możliwa zamiana SKLEP",
    "thumbnail": "https://www.olx.pl/app/static/media/no_thumbnail.c222b0530.svg",
    "url": "https://www.olx.pl/d/oferta/railway-empire-nintendo-switch-edition-mozliwa-zamiana-sklep-CID99-ID11lgXG.html",
    "pricePLN": "70 zł",
    "city": "Warszawa, Ursus",
    "type": "BUY_NOW",
    "date": "4.11.2024 10:08",
    "timestamp": 1730714880000
  },
  {
    "localId": 957140253,
    "title": "Mario Kart 8 Deluxe for Nintendo Switch",
    "thumbnail": "https://www.olx.pl/app/static/media/no_thumbnail.c222b0530.svg",
    "url": "https://www.olx.pl/d/oferta/mario-kart-8-deluxe-for-nintendo-switch-CID99-ID12M3U1.html",
    "pricePLN": "125 zł",
    "city": "Katowice, Załęska Hałda",
    "type": "BUY_NOW",
    "date": "Brynów cz. Zach.",
    "timestamp": null
  }
]