[
  {
    "localId": 953929199,
    "title": "Mariokart 8 Nintendo Switch",
    "thumbnail": "https://ireland.apollo.olxcdn.com/v1/files/zmx7kmxtp32u-PL/image;s=200x0;q=50",
    "url": "https://www.olx.pl/d/oferta/mariokart-8-nintendo-switch-CID99-ID12yAyP.html",
    "pricePLN": "175 zł",
    "city": "Sosnowiec",
    "type": "BUY_NOW",
    "date": "22.10.2024 09:11",
    "timestamp": 1729588260000
  },
  {
    "localId": 953927738,
    "title": "Nowa w folii Gra Nintendo Switch Mario Party Superstars",
    "thumbnail": "https://ireland.apollo.olxcdn.com/v1/files/qdu0tgr1cko22-PL/image;s=200x0;q=50",
    "url": "https://www.olx.pl/d/oferta/nowa-w-folii-gra-nintendo-switch-mario-party-superstars-CID99-ID12yAbg.html",
    "pricePLN": "185 zł",
    "city": "Sosnowiec",
    "type": "BUY_NOW",
    "date": "22.10.2024 09:07",
    "timestamp": 1729588020000
  },
  {
    "localId": 953927545,
    "title": "Najtaniej Gra Nintendo Switch Pokemon Sword wraz z pudełkiem",
    "thumbnail": "https://ireland.apollo.olxcdn.com/v1/files/2g9oq0ynm0wx1-PL/image;s=200x0;q=50",
    "url": "https://www.olx.pl/d/oferta/najtaniej-gra-nintendo-switch-pokemon-sword-wraz-z-pudelkiem-CID99-ID12yA89.html",
    "pricePLN": "139 zł",
    "city": "Gorzów Wielkopolski",
    "type": "BUY_NOW",
    "date": "22.10.2024 09:06",
    "timestamp": 1729587960000
  },
  {
    "localId": 953927415,
    "title": "Gra na konsole Marvel Ultimate Alliance 3 Nintendo Switch",
    "thumbnail": "https://ireland.apollo.olxcdn.com/v1/files/znm9ka01yjjm2-PL/image;s=200x0;q=50",
    "url": "https://www.olx.pl/d/oferta/gra-na-konsole-marvel-ultimate-alliance-3-nintendo-switch-CID99-ID12yA63.html",
    "pricePLN": "139 zł",
    "city": "Sosnowiec",
    "type": "BUY_NOW",
    "date": "22.10.2024 09:06",
    "timestamp": 1729587960000
  },
  {
    "localId": 953926192,
    "title": "Lego Brawls Nintendo Switch",
    "thumbnail": "https://ireland.apollo.olxcdn.com/v1/files/hck1jikl79lg-PL/image;s=200x0;q=50",
    "url": "https://www.olx.pl/d/oferta/lego-brawls-nintendo-switch-CID99-ID12yzMk.html",
    "pricePLN": "65 zł",
    "city": "Sosnowiec",
    "type": "BUY_NOW",
    "date": "22.10.2024 09:03",
    "timestamp": 1729587780000
  },
  {
    "localId": 953925807,
    "title": "Animal Crossing Nintendo Switch",
    "thumbnail": "https://www.olx.pl/app/static/media/no_thumbnail.c222b0530.svg",
    "url": "https://www.olx.pl/d/oferta/animal-crossing-nintendo-switch-CID99-ID12yzG7.html",
    "pricePLN": "119 zł",
    "city": "Sosnowiec",
    "type": "BUY_NOW",
    "date": "22.10.2024 09:01",
    "timestamp": 1729587660000
  },
  {
    "localId": 953924165,
    "title": "Gra na konsole Nintendo Switch Mario Odyssey",
    "thumbnail": "https://www.olx.pl/app/static/media/no_thumbnail.c222b0530.svg",
    "url": "https://www.olx.pl/d/oferta/gra-na-konsole-nintendo-switch-mario-odyssey-CID99-ID12yzfD.html",
    "pricePLN": "129 zł",
    "city": "Sosnowiec",
    "type": "BUY_NOW",
    "date": "22.10.2024 08:56",
    "timestamp": 1729587360000
  },
  {
    "localId": 953923563,
    "title": "Pokemon Sword Nintendo Switch",
    "thumbnail": "https://www.olx.pl/app/static/media/no_thumbnail.c222b0530.svg",
    "url": "https://www.olx.pl/d/oferta/pokemon-sword-nintendo-switch-CID99-ID12yz5W.html",
    "pricePLN": "149 zł",
    "city": "Sosnowiec",
    "type": "BUY_NOW",
    "date": "22.10.2024 08:55",
    "timestamp": 1729587300000
  },
  {
    "localId": 953916053,
    "title": "Pokemon Mystery Dungeon Rescue Team DX",
    "thumbnail": "https://www.olx.pl/app/static/media/no_thumbnail.c222b0530.svg",
    "url": "https://www.olx.pl/d/oferta/pokemon-mystery-dungeon-rescue-team-dx-CID99-ID12yx8N.html",
    "pricePLN": "200 zł",
    "city": "Warszawa, Wola",
    "type": "BUY_NOW",
    "date": "22.10.2024 08:33",
    "timestamp": 1729585980000
  },
  {
    "localId": 953915096,
    "title": "Darkest Dungeon 2 PL + dodatek! Nintendo Switch /Nowa w folii!",
    "thumbnail": "https://www.olx.pl/app/static/media/no_thumbnail.c222b0530.svg",
    "url": "https://www.olx.pl/d/oferta/darkest-dungeon-2-pl-dodatek-nintendo-switch-nowa-w-folii-CID99-ID12yvTm.html",
    "pricePLN": "189,99 zł",
    "city": "Chorzów",
    "type": "BUY_NOW",
    "date": "22.10.2024 08:31",
    "timestamp": 1729585860000
  },
  {
    "localId": 953913229,
    "title": "Zelda Link's Awakening jak nowa",
    "thumbnail": "https://www.olx.pl/app/static/media/no_thumbnail.c222b0530.svg",
    "url": "https://www.olx.pl/d/oferta/zelda-links-awakening-jak-nowa-CID99-ID12yvpf.html",
    "pricePLN": "178 zł",
    "city": "Zabrze",
    "type": "BUY_NOW",
    "date": "22.10.2024 08:24",
    "timestamp": 1729585440000
  },
  {
    "localId": 953910840,
    "title": "Darkest dungeon 2 Nintendo Switch",
    "thumbnail": "https://www.olx.pl/app/static/media/no_thumbnail.c222b0530.svg",
    "url": "https://www.olx.pl/d/oferta/darkest-dungeon-2-nintendo-switch-CID99-ID12ywMI.html",
    "pricePLN": "130 zł",
    "city": "Kuznocin",
    "type": "BUY_NOW",
    "date": "22.10.2024 08:18",
    "timestamp": 1729585080000
  },
  {
    "localId": 953908195,
    "title": "Super Mario Maker 2 Nintendo Switch",
    "thumbnail": "https://www.olx.pl/app/static/media/no_thumbnail.c222b0530.svg",
    "url": "https://www.olx.pl/d/oferta/super-mario-maker-2-nintendo-switch-CID99-ID12yw63.html",
    "pricePLN": "100 zł",
    "city": "Poznań, Starołęka",
    "type": "BUY_NOW",
    "date": "22.10.2024 08:10",
    "timestamp": 1729584600000
  },
  {
    "localId": 939608824,
    "title": "Gra Nintendo Switch Darksiders Genesis Edition stan bdb",
    "thumbnail": "https://www.olx.pl/app/static/media/no_thumbnail.c222b0530.svg",
    "url": "https://www.olx.pl/d/oferta/gra-nintendo-switch-darksiders-genesis-edition-stan-bdb-CID99-ID11Awb2.html",
    "pricePLN": "132 zł",
    "city": "Białystok, Nowe Miasto",
    "type": "BUY_NOW",
    "date": "22.10.2024 08:08",
    "timestamp": 1729584480000
  },
  {
    "localId": 953907646,
    "title": "Super Mario Odyssey Nintendo Switch",
    "thumbnail": "https://www.olx.pl/app/static/media/no_thumbnail.c222b0530.svg",
    "url": "https://www.olx.pl/d/oferta/super-mario-odyssey-nintendo-switch-CID99-ID12yuXc.html",
    "pricePLN": "100 zł",
    "city": "Poznań, Starołęka",
    "type": "BUY_NOW",
    "date": "22.10.2024 08:08",
    "timestamp": 1729584480000
  },
  {
    "localId": 953906278,
    "title": "Darkest dungeon 2 Nintendo switch nowa w folii",
    "thumbnail": "https://www.olx.pl/app/static/media/no_thumbnail.c222b0530.svg",
    "url": "https://www.olx.pl/d/oferta/darkest-dungeon-2-nintendo-switch-nowa-w-folii-CID99-ID12yuB8.html",
    "pricePLN": "135 zł",
    "city": "Kamień Mały",
    "type": "BUY_NOW",
    "date": "22.10.2024 08:04",
    "timestamp": 1729584240000
  },
  {
    "localId": 953905452,
    "title": "Metroid Prime Remastered Nintendo Switch NOWA FOLIA",
    "thumbnail": "https://www.olx.pl/app/static/media/no_thumbnail.c222b0530.svg",
    "url": "https://www.olx.pl/d/oferta/metroid-prime-remastered-nintendo-switch-nowa-folia-CID99-ID12yunO.html",
    "pricePLN": "100 zł",
    "city": "Poznań, Starołęka",
    "type": "BUY_NOW",
    "date": "22.10.2024 08:01",
    "timestamp": 1729584060000
  },
  {
    "localId": 953904462,
    "title": "Super Mario Odyssey - gra na Nintendo Switch",
    "thumbnail": "https://www.olx.pl/app/static/media/no_thumbnail.c222b0530.svg",
    "url": "https://www.olx.pl/d/oferta/super-mario-odyssey-gra-na-nintendo-switch-CID99-ID12yu7Q.html",
    "pricePLN": "145 zł",
    "city": "Jarocin",
    "type": "BUY_NOW",
    "date": "22.10.2024 07:57",
    "timestamp": 1729583820000
  },
  {
    "localId": 953904104,
    "title": "The Legend of Zelda: Tears of the Kingdom (Nintendo Switch)",
    "thumbnail": "https://www.olx.pl/app/static/media/no_thumbnail.c222b0530.svg",
    "url": "https://www.olx.pl/d/oferta/the-legend-of-zelda-tears-of-the-kingdom-nintendo-switch-CID99-ID12yu24.html",
    "pricePLN": "159 zł",
    "city": "Jarocin",
    "type": "BUY_NOW",
    "date": "22.10.2024 07:56",
    "timestamp": 1729583760000
  },
  {
    "localId": 953904063,
    "title": "LEGO City, Nintendo switch używane",
    "thumbnail": "https://www.olx.pl/app/static/media/no_thumbnail.c222b0530.svg",
    "url": "https://www.olx.pl/d/oferta/lego-city-nintendo-switch-uzywane-CID99-ID12yu1p.html",
    "pricePLN": "100 zł",
    "city": "Buczkowice",
    "type": "BUY_NOW",
    "date": "22.10.2024 07:55",
    "timestamp": 1729583700000
  },
  {
    "localId": 953903051,
    "title": "The Legend of Zelda Link's Awakening Nintendo Switch",
    "thumbnail": "https://www.olx.pl/app/static/media/no_thumbnail.c222b0530.svg",
    "url": "https://www.olx.pl/d/oferta/the-legend-of-zelda-links-awakening-nintendo-switch-CID99-ID12ytL5.html",
    "pricePLN": "150 zł",
    "city": "Poznań, Starołęka",
    "type": "BUY_NOW",
    "date": "22.10.2024 07:51",
    "timestamp": 1729583460000
  },
  {
    "localId": 953902696,
    "title": "Hyrule Warriors Age of Calamity Nintendo Switch",
    "thumbnail": "https://www.olx.pl/app/static/media/no_thumbnail.c222b0530.svg",
    "url": "https://www.olx.pl/d/oferta/hyrule-warriors-age-of-calamity-nintendo-switch-CID99-ID12ytFm.html",
    "pricePLN": "100 zł",
    "city": "Poznań, Starołęka",
    "type": "BUY_NOW",
    "date": "22.10.2024 07:50",
    "timestamp": 1729583400000
  },
  {
    "localId": 933080666,
    "title": "ZELDA Tears of the Kingdom",
    "thumbnail": "https://www.olx.pl/app/static/media/no_thumbnail.c222b0530.svg",
    "url": "https://www.olx.pl/d/oferta/zelda-tears-of-the-kingdom-CID99-ID1196Ua.html",
    "pricePLN": "440 zł",
    "city": "Bytom",
    "type": "BUY_NOW",
    "date": "22.10.2024 07:45",
    "timestamp": 1729583100000
  },
  {
    "localId": 953900469,
    "title": "Mario Kart 8 Deluxe Nintendo Switch",
    "thumbnail": "https://www.olx.pl/app/static/media/no_thumbnail.c222b0530.svg",
    "url": "https://www.olx.pl/d/oferta/mario-kart-8-deluxe-nintendo-switch-CID99-ID12yt5r.html",
    "pricePLN": "100 zł",
    "city": "Poznań, Starołęka",
    "type": "BUY_NOW",
    "date": "22.10.2024 07:41",
    "timestamp": 1729582860000
  },
  {
    "localId": 953898915,
    "title": "Super Mario Party Nintendo Switch",
    "thumbnail": "https://www.olx.pl/app/static/media/no_thumbnail.c222b0530.svg",
    "url": "https://www.olx.pl/d/oferta/super-mario-party-nintendo-switch-CID99-ID12ysGn.html",
    "pricePLN": "100 zł",
    "city": "Poznań, Starołęka",
    "type": "BUY_NOW",
    "date": "22.10.2024 07:36",
    "timestamp": 1729582560000
  },
  {
    "localId": 953898510,
    "title": "Paper Mario Origami King Nintendo Switch",
    "thumbnail": "https://www.olx.pl/app/static/media/no_thumbnail.c222b0530.svg",
    "url": "https://www.olx.pl/d/oferta/paper-mario-origami-king-nintendo-switch-CID99-ID12yszQ.html",
    "pricePLN": "100 zł",
    "city": "Poznań, Starołęka",
    "type": "BUY_NOW",
    "date": "22.10.2024 07:34",
    "timestamp": 1729582440000
  },
  {
    "localId": 953897806,
    "title": "Bayonetta 2 Nintendo Switch",
    "thumbnail": "https://www.olx.pl/app/static/media/no_thumbnail.c222b0530.svg",
    "url": "https://www.olx.pl/d/oferta/bayonetta-2-nintendo-switch-CID99-ID12ysou.html",
    "pricePLN": "100 zł",
    "city": "Poznań, Starołęka",
    "type": "BUY_NOW",
    "date": "22.10.2024 07:31",
    "timestamp": 1729582260000
  },
  {
    "localId": 953895549,
    "title": "Gry Nintendo Switch",
    "thumbnail": "https://www.olx.pl/app/static/media/no_thumbnail.c222b0530.svg",
    "url": "https://www.olx.pl/d/oferta/gry-nintendo-switch-CID99-ID12yrO5.html",
    "pricePLN": "550 zł\ndo negocjacji",
    "city": "Charwatynia",
    "type": "BUY_NOW",
    "date": "22.10.2024 07:22",
    "timestamp": 1729581720000
  },
  {
    "localId": 953894546,
    "title": "Xenoblade Chronicles 3",
    "thumbnail": "https://www.olx.pl/app/static/media/no_thumbnail.c222b0530.svg",
    "url": "https://www.olx.pl/d/oferta/xenoblade-chronicles-3-CID99-ID12yrxU.html",
    "pricePLN": "119,99 zł",
    "city": "Rowy",
    "type": "BUY_NOW",
    "date": "22.10.2024 07:18",
    "timestamp": 1729581480000
  },
  {
    "localId": 953893785,
    "title": "Świetna gra Mario Kart 8 Deluxe Nintendo",
    "thumbnail": "https://www.olx.pl/app/static/media/no_thumbnail.c222b0530.svg",
    "url": "https://www.olx.pl/d/oferta/swietna-gra-mario-kart-8-deluxe-nintendo-CID99-ID12yrlD.html",
    "pricePLN": "149 zł",
    "city": "Lublin",
    "type": "BUY_NOW",
    "date": "22.10.2024 07:15",
    "timestamp": 1729581300000
  },
  {
    "localId": 953888189,
    "title": "Morbid The Lords of Ire - Nintendo Switch.",
    "thumbnail": "https://www.olx.pl/app/static/media/no_thumbnail.c222b0530.svg",
    "url": "https://www.olx.pl/d/oferta/morbid-the-lords-of-ire-nintendo-switch-CID99-ID12ypTn.html",
    "pricePLN": "99 zł",
    "city": "Rzeszów",
    "type": "BUY_NOW",
    "date": "22.10.2024 07:01",
    "timestamp": 1729580460000
  },
  {
    "localId": 953886982,
    "title": "Dodonpachi Ressurrection Edycja Limitowana - Nintendo Switch JPN NOWA",
    "thumbnail": "https://www.olx.pl/app/static/media/no_thumbnail.c222b0530.svg",
    "url": "https://www.olx.pl/d/oferta/dodonpachi-ressurrection-edycja-limitowana-nintendo-switch-jpn-nowa-CID99-ID12ypzU.html",
    "pricePLN": "200 zł\ndo negocjacji",
    "city": "Kraków, Podgórze",
    "type": "BUY_NOW",
    "date": "22.10.2024 06:58",
    "timestamp": 1729580280000
  },
  {
    "localId": 953886396,
    "title": "nintendo world championships nes edition nintendo switch",
    "thumbnail": "https://www.olx.pl/app/static/media/no_thumbnail.c222b0530.svg",
    "url": "https://www.olx.pl/d/oferta/nintendo-world-championships-nes-edition-nintendo-switch-CID99-ID12ypqs.html",
    "pricePLN": "130 zł",
    "city": "Łaziska Górne, Łaziska",
    "type": "BUY_NOW",
    "date": "Centrum",
    "timestamp": null
  },
  {
    "localId": 953886267,
    "title": "Operation Wolf Returns First Mission - Nintendo Switch.",
    "thumbnail": "https://www.olx.pl/app/static/media/no_thumbnail.c222b0530.svg",
    "url": "https://www.olx.pl/d/oferta/operation-wolf-returns-first-mission-nintendo-switch-CID99-ID12ypon.html",
    "pricePLN": "79 zł",
    "city": "Rzeszów",
    "type": "BUY_NOW",
    "date": "22.10.2024 06:57",
    "timestamp": 1729580220000
  },
  {
    "localId": 953885517,
    "title": "Darius Cozmic Collection - Nintendo Switch JPN NOWA",
    "thumbnail": "https://www.olx.pl/app/static/media/no_thumbnail.c222b0530.svg",
    "url": "https://www.olx.pl/d/oferta/darius-cozmic-collection-nintendo-switch-jpn-nowa-CID99-ID12ypch.html",
    "pricePLN": "180 zł\ndo negocjacji",
    "city": "Kraków, Podgórze",
    "type": "BUY_NOW",
    "date": "22.10.2024 06:56",
    "timestamp": 1729580160000
  },
  {
    "localId": 953883839,
    "title": "Raiden III X Mikado Maniax - Nintendo Switch JPN NOWA",
    "thumbnail": "https://www.olx.pl/app/static/media/no_thumbnail.c222b0530.svg",
    "url": "https://www.olx.pl/d/oferta/raiden-iii-x-mikado-maniax-nintendo-switch-jpn-nowa-CID99-ID12yoLd.html",
    "pricePLN": "150 zł\ndo negocjacji",
    "city": "Kraków, Podgórze",
    "type": "BUY_NOW",
    "date": "22.10.2024 06:53",
    "timestamp": 1729579980000
  },
  {
    "localId": 946570627,
    "title": "GRA ENDLING Nintendo Switch",
    "thumbnail": "https://www.olx.pl/app/static/media/no_thumbnail.c222b0530.svg",
    "url": "https://www.olx.pl/d/oferta/gra-endling-nintendo-switch-CID99-ID123Igb.html",
    "pricePLN": "70 zł",
    "city": "Brzostowa Góra",
    "type": "BUY_NOW",
    "date": "22.10.2024 06:27",
    "timestamp": 1729578420000
  },
  {
    "localId": 939585493,
    "title": "Miraculous Biedronka i Czarny Kot. Gra Nintendo",
    "thumbnail": "https://www.olx.pl/app/static/media/no_thumbnail.c222b0530.svg",
    "url": "https://www.olx.pl/d/oferta/miraculous-biedronka-i-czarny-kot-gra-nintendo-CID99-ID11Ap6J.html",
    "pricePLN": "90 zł",
    "city": "Warszawa, Bielany",
    "type": "BUY_NOW",
    "date": "22.10.2024 06:26",
    "timestamp": 1729578360000
  },
  {
    "localId": 953874568,
    "title": "Świetna gierka Super Mario Bros Wonder Nintendo Switch",
    "thumbnail": "https://www.olx.pl/app/static/media/no_thumbnail.c222b0530.svg",
    "url": "https://www.olx.pl/d/oferta/swietna-gierka-super-mario-bros-wonder-nintendo-switch-CID99-ID12ymlG.html",
    "pricePLN": "129 zł",
    "city": "Lublin",
    "type": "BUY_NOW",
    "date": "22.10.2024 06:19",
    "timestamp": 1729577940000
  },
  {
    "localId": 953873511,
    "title": "Sifu Vengeance Edition - Nintendo Switch.",
    "thumbnail": "https://www.olx.pl/app/static/media/no_thumbnail.c222b0530.svg",
    "url": "https://www.olx.pl/d/oferta/sifu-vengeance-edition-nintendo-switch-CID99-ID12ym4D.html",
    "pricePLN": "99 zł",
    "city": "Rzeszów",
    "type": "BUY_NOW",
    "date": "22.10.2024 06:08",
    "timestamp": 1729577280000
  }
]