[
  {
    "localId": 932122948,
    "title": "Gra Splatoon 3 Nintendo Switch",
    "thumbnail": "https://ireland.apollo.olxcdn.com/v1/files/eyubskvofm1t-PL/image;s=200x0;q=50",
    "url": "https://www.olx.pl/d/oferta/gra-splatoon-3-nintendo-switch-CID99-ID1155L6.html",
    "pricePLN": "150 zł",
    "city": "Bojanów",
    "type": "BUY_NOW",
    "productType": "USED",
    "date": "19.7.2024 14:40",
    "timestamp": 1721400000000
  },
  {
    "localId": 932122660,
    "title": "Dead cells nintendo Switch",
    "thumbnail": "https://ireland.apollo.olxcdn.com/v1/files/209sd27gmpg43-PL/image;s=200x0;q=50",
    "url": "https://www.olx.pl/d/oferta/dead-cells-nintendo-switch-CID99-ID1155Gs.html",
    "pricePLN": "110 zł",
    "city": "Bojanów",
    "type": "BUY_NOW",
    "productType": "USED",
    "date": "19.7.2024 14:38",
    "timestamp": 1721399880000
  },
  {
    "localId": 932122242,
    "title": "Cult of the lamb Nintendo Switch",
    "thumbnail": "https://ireland.apollo.olxcdn.com/v1/files/0skwox2ip9bl1-PL/image;s=200x0;q=50",
    "url": "https://www.olx.pl/d/oferta/cult-of-the-lamb-nintendo-switch-CID99-ID1155zI.html",
    "pricePLN": "100 zł",
    "city": "Bojanów",
    "type": "BUY_NOW",
    "productType": "USED",
    "date": "19.7.2024 14:36",
    "timestamp": 1721399760000
  },
  {
    "localId": 932122029,
    "title": "Mario Rabbids Sparks of Hope",
    "thumbnail": "https://ireland.apollo.olxcdn.com/v1/files/xri3w6jxr4pk2-PL/image;s=200x0;q=50",
    "url": "https://www.olx.pl/d/oferta/mario-rabbids-sparks-of-hope-CID99-ID1155vh.html",
    "pricePLN": "70 zł",
    "city": "Bojanów",
    "type": "BUY_NOW",
    "productType": "USED",
    "date": "19.7.2024 14:35",
    "timestamp": 1721399700000
  },
  {
    "localId": 932121781,
    "title": "Shovel knight treasure trove",
    "thumbnail": "https://ireland.apollo.olxcdn.com/v1/files/vt8e9ydxql2k3-PL/image;s=200x0;q=50",
    "url": "https://www.olx.pl/d/oferta/shovel-knight-treasure-trove-CID99-ID1155sh.html",
    "pricePLN": "70 zł",
    "city": "Kielce",
    "type": "BUY_NOW",
    "productType": "USED",
    "date": "19.7.2024 14:34",
    "timestamp": 1721399640000
  },
  {
    "localId": 932121522,
    "title": "Pokemon Tekken DX",
    "thumbnail": "https://www.olx.pl/app/static/media/no_thumbnail.c222b0530.svg",
    "url": "https://www.olx.pl/d/oferta/pokemon-tekken-dx-CID99-ID1155o6.html",
    "pricePLN": "170 zł",
    "city": "Kielce",
    "type": "BUY_NOW",
    "productType": "USED",
    "date": "19.7.2024 14:32",
    "timestamp": 1721399520000
  },
  {
    "localId": 932120487,
    "title": "LEGO Star Wars The Skywalker Saga",
    "thumbnail": "https://www.olx.pl/app/static/media/no_thumbnail.c222b0530.svg",
    "url": "https://www.olx.pl/d/oferta/lego-star-wars-the-skywalker-saga-CID99-ID11557p.html",
    "pricePLN": "80 zł",
    "city": "Piaseczno",
    "type": "BUY_NOW",
    "productType": "USED",
    "date": "19.7.2024 14:27",
    "timestamp": 1721399220000
  },
  {
    "localId": 932118997,
    "title": "Just Dance 2022 Nintendo Switch",
    "thumbnail": "https://www.olx.pl/app/static/media/no_thumbnail.c222b0530.svg",
    "url": "https://www.olx.pl/d/oferta/just-dance-2022-nintendo-switch-CID99-ID1154Jn.html",
    "pricePLN": "70 zł",
    "city": "Marki",
    "type": "BUY_NOW",
    "productType": "USED",
    "date": "19.7.2024 14:19",
    "timestamp": 1721398740000
  },
  {
    "localId": 932118388,
    "title": "Pokemon Violet Nintendo Switch",
    "thumbnail": "https://www.olx.pl/app/static/media/no_thumbnail.c222b0530.svg",
    "url": "https://www.olx.pl/d/oferta/pokemon-violet-nintendo-switch-CID99-ID1154zy.html",
    "pricePLN": "120 zł",
    "city": "Marki",
    "type": "BUY_NOW",
    "productType": "USED",
    "date": "19.7.2024 14:16",
    "timestamp": 1721398560000
  },
  {
    "localId": 932116270,
    "title": "Mario Kart 8 Deluxe Nintendo Switch",
    "thumbnail": "https://www.olx.pl/app/static/media/no_thumbnail.c222b0530.svg",
    "url": "https://www.olx.pl/d/oferta/mario-kart-8-deluxe-nintendo-switch-CID99-ID11541o.html",
    "pricePLN": "165 zł",
    "city": "Kielce",
    "type": "BUY_NOW",
    "productType": "USED",
    "date": "19.7.2024 14:06",
    "timestamp": 1721397960000
  },
  {
    "localId": 932094966,
    "title": "Switch Blacksad Under The Skin Limited Edition Nowa Nintendo Switch",
    "thumbnail": "",
    "url": "https://www.olx.pl/d/oferta/switch-blacksad-under-the-skin-limited-edition-nowa-nintendo-switch-CID99-ID114YtM.html",
    "pricePLN": "69 zł",
    "city": "Poznań, Jeżyce",
    "type": "BUY_NOW",
    "productType": "NEW",
    "date": "19.7.2024 14:04",
    "timestamp": 1721397840000
  },
  {
    "localId": 932114310,
    "title": "The legend of Zelda breath of the wild Nintendo Switch",
    "thumbnail": "https://www.olx.pl/app/static/media/no_thumbnail.c222b0530.svg",
    "url": "https://www.olx.pl/d/oferta/the-legend-of-zelda-breath-of-the-wild-nintendo-switch-CID99-ID1153wM.html",
    "pricePLN": "155 zł",
    "city": "Kielce",
    "type": "BUY_NOW",
    "productType": "USED",
    "date": "19.7.2024 13:58",
    "timestamp": 1721397480000
  },
  {
    "localId": 932113090,
    "title": "Kirby's Return to DreamLand Deluxe - Nintendo Switch",
    "thumbnail": "https://www.olx.pl/app/static/media/no_thumbnail.c222b0530.svg",
    "url": "https://www.olx.pl/d/oferta/kirbys-return-to-dreamland-deluxe-nintendo-switch-CID99-ID1153c6.html",
    "pricePLN": "165 zł",
    "city": "Kielce",
    "type": "BUY_NOW",
    "productType": "USED",
    "date": "19.7.2024 13:53",
    "timestamp": 1721397180000
  },
  {
    "localId": 932112461,
    "title": "Mario Strikes Battle league football Nintendo Switch",
    "thumbnail": "https://www.olx.pl/app/static/media/no_thumbnail.c222b0530.svg",
    "url": "https://www.olx.pl/d/oferta/mario-strikes-battle-league-football-nintendo-switch-CID99-ID11531X.html",
    "pricePLN": "110 zł",
    "city": "Kielce",
    "type": "BUY_NOW",
    "productType": "USED",
    "date": "19.7.2024 13:50",
    "timestamp": 1721397000000
  },
  {
    "localId": 932081898,
    "title": "Zestaw gier Nintendo switch gry Krakow",
    "thumbnail": "https://www.olx.pl/app/static/media/no_thumbnail.c222b0530.svg",
    "url": "https://www.olx.pl/d/oferta/zestaw-gier-nintendo-switch-gry-krakow-CID99-ID114W50.html",
    "pricePLN": "1 zł",
    "city": "Pękowice",
    "type": "BUY_NOW",
    "productType": "NEW",
    "date": "19.7.2024 13:45",
    "timestamp": 1721396700000
  },
  {
    "localId": 932106934,
    "title": "Kirby and the Forgotten Land Nintendo Switch",
    "thumbnail": "https://www.olx.pl/app/static/media/no_thumbnail.c222b0530.svg",
    "url": "https://www.olx.pl/d/oferta/kirby-and-the-forgotten-land-nintendo-switch-CID99-ID1151AO.html",
    "pricePLN": "165 zł",
    "city": "Wrocław, Krzyki",
    "type": "BUY_NOW",
    "productType": "USED",
    "date": "19.7.2024 13:25",
    "timestamp": 1721395500000
  },
  {
    "localId": 932104725,
    "title": "Gra Nintendo konsola przenośna /tv",
    "thumbnail": "https://www.olx.pl/app/static/media/no_thumbnail.c222b0530.svg",
    "url": "https://www.olx.pl/d/oferta/gra-nintendo-konsola-przenosna-tv-CID99-ID11511b.html",
    "pricePLN": "1 000 zł",
    "city": "Łuszczanowice",
    "type": "BUY_NOW",
    "productType": "USED",
    "date": "19.7.2024 13:14",
    "timestamp": 1721394840000
  },
  {
    "localId": 932097283,
    "title": "Switch Destroy All Humans! PL Napisy Nintendo Switch",
    "thumbnail": "",
    "url": "https://www.olx.pl/d/oferta/switch-destroy-all-humans-pl-napisy-nintendo-switch-CID99-ID114Z59.html",
    "pricePLN": "99 zł",
    "city": "Poznań, Jeżyce",
    "type": "BUY_NOW",
    "productType": "NEW",
    "date": "19.7.2024 12:41",
    "timestamp": 1721392860000
  },
  {
    "localId": 932097101,
    "title": "Nintendo Switch Sports",
    "thumbnail": "https://www.olx.pl/app/static/media/no_thumbnail.c222b0530.svg",
    "url": "https://www.olx.pl/d/oferta/nintendo-switch-sports-CID99-ID114Z2d.html",
    "pricePLN": "155 zł",
    "city": "Wrocław, Psie Pole",
    "type": "BUY_NOW",
    "productType": "USED",
    "date": "19.7.2024 12:40",
    "timestamp": 1721392800000
  },
  {
    "localId": 932096856,
    "title": "Switch Pokemon Tournament DX Nintendo Switch",
    "thumbnail": "",
    "url": "https://www.olx.pl/d/oferta/switch-pokemon-tournament-dx-nintendo-switch-CID99-ID114YYg.html",
    "pricePLN": "199 zł",
    "city": "Poznań, Jeżyce",
    "type": "BUY_NOW",
    "productType": "NEW",
    "date": "19.7.2024 12:39",
    "timestamp": 1721392740000
  },
  {
    "localId": 932096812,
    "title": "Nintendo Switch FC 24",
    "thumbnail": "https://www.olx.pl/app/static/media/no_thumbnail.c222b0530.svg",
    "url": "https://www.olx.pl/d/oferta/nintendo-switch-fc-24-CID99-ID114YXy.html",
    "pricePLN": "125 zł",
    "city": "Wrocław, Psie Pole",
    "type": "BUY_NOW",
    "productType": "USED",
    "date": "19.7.2024 12:39",
    "timestamp": 1721392740000
  },
  {
    "localId": 932096449,
    "title": "Switch Pokemon Lets Go Pikachu Nintendo Switch",
    "thumbnail": "",
    "url": "https://www.olx.pl/d/oferta/switch-pokemon-lets-go-pikachu-nintendo-switch-CID99-ID114YRH.html",
    "pricePLN": "169 zł",
    "city": "Poznań, Jeżyce",
    "type": "BUY_NOW",
    "productType": "USED",
    "date": "19.7.2024 12:38",
    "timestamp": 1721392680000
  },
  {
    "localId": 932096102,
    "title": "Switch EA Sports FC 24 FIFA PL Komentarze Nintendo Switch",
    "thumbnail": "",
    "url": "https://www.olx.pl/d/oferta/switch-ea-sports-fc-24-fifa-pl-komentarze-nintendo-switch-CID99-ID114YM6.html",
    "pricePLN": "129 zł",
    "city": "Poznań, Jeżyce",
    "type": "BUY_NOW",
    "productType": "NEW",
    "date": "19.7.2024 12:36",
    "timestamp": 1721392560000
  },
  {
    "localId": 932095680,
    "title": "Switch Super Mario RPG Nintendo Switch",
    "thumbnail": "https://www.olx.pl/app/static/media/no_thumbnail.c222b0530.svg",
    "url": "https://www.olx.pl/d/oferta/switch-super-mario-rpg-nintendo-switch-CID99-ID114YFi.html",
    "pricePLN": "129 zł",
    "city": "Poznań, Jeżyce",
    "type": "BUY_NOW",
    "productType": "USED",
    "date": "19.7.2024 12:34",
    "timestamp": 1721392440000
  },
  {
    "localId": 932094643,
    "title": "Pet Clinic Cats&Dogs Nintendo Switch",
    "thumbnail": "https://www.olx.pl/app/static/media/no_thumbnail.c222b0530.svg",
    "url": "https://www.olx.pl/d/oferta/pet-clinic-cats-dogs-nintendo-switch-CID99-ID114Yoz.html",
    "pricePLN": "30 zł",
    "city": "Komorniki",
    "type": "BUY_NOW",
    "productType": "USED",
    "date": "19.7.2024 12:29",
    "timestamp": 1721392140000
  },
  {
    "localId": 932094585,
    "title": "Switch Zombieland Double Tap Roadtrip Nowa Folia Nintendo Switch",
    "thumbnail": "https://www.olx.pl/app/static/media/no_thumbnail.c222b0530.svg",
    "url": "https://www.olx.pl/d/oferta/switch-zombieland-double-tap-roadtrip-nowa-folia-nintendo-switch-CID99-ID114YnD.html",
    "pricePLN": "199 zł",
    "city": "Poznań, Jeżyce",
    "type": "BUY_NOW",
    "productType": "NEW",
    "date": "19.7.2024 12:29",
    "timestamp": 1721392140000
  },
  {
    "localId": 932094338,
    "title": "Nintendo switch Pokemon Arceus",
    "thumbnail": "https://www.olx.pl/app/static/media/no_thumbnail.c222b0530.svg",
    "url": "https://www.olx.pl/d/oferta/nintendo-switch-pokemon-arceus-CID99-ID114YjE.html",
    "pricePLN": "179 zł",
    "city": "Lędziny, Blich",
    "type": "BUY_NOW",
    "productType": "USED",
    "date": "19.7.2024 12:28",
    "timestamp": 1721392080000
  },
  {
    "localId": 932094015,
    "title": "Nintendo switch Pokemon Pikachu",
    "thumbnail": "https://www.olx.pl/app/static/media/no_thumbnail.c222b0530.svg",
    "url": "https://www.olx.pl/d/oferta/nintendo-switch-pokemon-pikachu-CID99-ID114Yer.html",
    "pricePLN": "179 zł",
    "city": "Lędziny, Blich",
    "type": "BUY_NOW",
    "productType": "USED",
    "date": "19.7.2024 12:27",
    "timestamp": 1721392020000
  },
  {
    "localId": 932093870,
    "title": "Nintendo switch Pokemon Scarlet",
    "thumbnail": "https://www.olx.pl/app/static/media/no_thumbnail.c222b0530.svg",
    "url": "https://www.olx.pl/d/oferta/nintendo-switch-pokemon-scarlet-CID99-ID114Yc6.html",
    "pricePLN": "179 zł",
    "city": "Lędziny, Blich",
    "type": "BUY_NOW",
    "productType": "USED",
    "date": "19.7.2024 12:26",
    "timestamp": 1721391960000
  },
  {
    "localId": 932086039,
    "title": "Pokemon Shield / Nintendo Switch *Sklep Bytom",
    "thumbnail": "https://www.olx.pl/app/static/media/no_thumbnail.c222b0530.svg",
    "url": "https://www.olx.pl/d/oferta/pokemon-shield-nintendo-switch-sklep-bytom-CID99-ID114V9N.html",
    "pricePLN": "159,99 zł",
    "city": "Bytom",
    "type": "BUY_NOW",
    "productType": "USED",
    "date": "19.7.2024 11:55",
    "timestamp": 1721390100000
  },
  {
    "localId": 932086100,
    "title": "Teenage Mutant Ninja Turtles: The Cowabunga Collection nintendo Switch",
    "thumbnail": "https://www.olx.pl/app/static/media/no_thumbnail.c222b0530.svg",
    "url": "https://www.olx.pl/d/oferta/teenage-mutant-ninja-turtles-the-cowabunga-collection-nintendo-switch-CID99-ID114VaM.html",
    "pricePLN": "50 zł",
    "city": "Komorniki",
    "type": "BUY_NOW",
    "productType": "USED",
    "date": "19.7.2024 11:55",
    "timestamp": 1721390100000
  },
  {
    "localId": 932085306,
    "title": "The Legend of Zelda Tears od the Kingdom Switch.",
    "thumbnail": "https://www.olx.pl/app/static/media/no_thumbnail.c222b0530.svg",
    "url": "https://www.olx.pl/d/oferta/the-legend-of-zelda-tears-od-the-kingdom-switch-CID99-ID114WXY.html",
    "pricePLN": "150 zł",
    "city": "Gdynia, Chylonia",
    "type": "BUY_NOW",
    "productType": "USED",
    "date": "19.7.2024 11:52",
    "timestamp": 1721389920000
  },
  {
    "localId": 932085179,
    "title": "Mario+ Rabbids Sparks of Hope nintendo Switch",
    "thumbnail": "https://www.olx.pl/app/static/media/no_thumbnail.c222b0530.svg",
    "url": "https://www.olx.pl/d/oferta/mario-rabbids-sparks-of-hope-nintendo-switch-CID99-ID114WWW.html",
    "pricePLN": "85 zł",
    "city": "Komorniki",
    "type": "BUY_NOW",
    "productType": "USED",
    "date": "19.7.2024 11:52",
    "timestamp": 1721389920000
  },
  {
    "localId": 932084927,
    "title": "STAR WARS Heritage Pack - 7 gier Nintendo Swich - Okazja!",
    "thumbnail": "https://www.olx.pl/app/static/media/no_thumbnail.c222b0530.svg",
    "url": "https://www.olx.pl/d/oferta/star-wars-heritage-pack-7-gier-nintendo-swich-okazja-CID99-ID114WRR.html",
    "pricePLN": "159 zł",
    "city": "Kluczbork",
    "type": "BUY_NOW",
    "productType": "USED",
    "date": "19.7.2024 11:51",
    "timestamp": 1721389860000
  },
  {
    "localId": 932081969,
    "title": "Dwie gry na nintendo switch. Fashion dreamer i story of seasons zestaw",
    "thumbnail": "https://www.olx.pl/app/static/media/no_thumbnail.c222b0530.svg",
    "url": "https://www.olx.pl/d/oferta/dwie-gry-na-nintendo-switch-fashion-dreamer-i-story-of-seasons-zestaw-CID99-ID114W69.html",
    "pricePLN": "220 zł",
    "city": "Łódź, Bałuty",
    "type": "BUY_NOW",
    "productType": "USED",
    "date": "19.7.2024 11:39",
    "timestamp": 1721389140000
  },
  {
    "localId": 932080633,
    "title": "Super Mario Wonder Nintendo Switch",
    "thumbnail": "https://www.olx.pl/app/static/media/no_thumbnail.c222b0530.svg",
    "url": "https://www.olx.pl/d/oferta/super-mario-wonder-nintendo-switch-CID99-ID114UKB.html",
    "pricePLN": "120 zł",
    "city": "Komorniki",
    "type": "BUY_NOW",
    "productType": "USED",
    "date": "19.7.2024 11:34",
    "timestamp": 1721388840000
  },
  {
    "localId": 932080150,
    "title": "Mario & Sonic Olimpic Games Nintendo Switch",
    "thumbnail": "https://www.olx.pl/app/static/media/no_thumbnail.c222b0530.svg",
    "url": "https://www.olx.pl/d/oferta/mario-sonic-olimpic-games-nintendo-switch-CID99-ID114UCO.html",
    "pricePLN": "179 zł",
    "city": "Sosnowiec",
    "type": "BUY_NOW",
    "productType": "USED",
    "date": "19.7.2024 11:32",
    "timestamp": 1721388720000
  },
  {
    "localId": 932079995,
    "title": "Pokemon Let's go Pikatchu Nintendo Switch",
    "thumbnail": "https://www.olx.pl/app/static/media/no_thumbnail.c222b0530.svg",
    "url": "https://www.olx.pl/d/oferta/pokemon-lets-go-pikatchu-nintendo-switch-CID99-ID114UAj.html",
    "pricePLN": "150 zł",
    "city": "Komorniki",
    "type": "BUY_NOW",
    "productType": "USED",
    "date": "19.7.2024 11:31",
    "timestamp": 1721388660000
  },
  {
    "localId": 932080034,
    "title": "Gra na konsole pokemon Violet Nintendo Switch",
    "thumbnail": "https://www.olx.pl/app/static/media/no_thumbnail.c222b0530.svg",
    "url": "https://www.olx.pl/d/oferta/gra-na-konsole-pokemon-violet-nintendo-switch-CID99-ID114UAV.html",
    "pricePLN": "129 zł",
    "city": "Sosnowiec",
    "type": "BUY_NOW",
    "productType": "USED",
    "date": "19.7.2024 11:31",
    "timestamp": 1721388660000
  },
  {
    "localId": 932079865,
    "title": "Pokemon Scarlet Nintendo Switch",
    "thumbnail": "https://www.olx.pl/app/static/media/no_thumbnail.c222b0530.svg",
    "url": "https://www.olx.pl/d/oferta/pokemon-scarlet-nintendo-switch-CID99-ID114Uyd.html",
    "pricePLN": "169 zł",
    "city": "Sosnowiec",
    "type": "BUY_NOW",
    "productType": "USED",
    "date": "19.7.2024 11:31",
    "timestamp": 1721388660000
  }
]