[
  {
    "localId": 931004296,
    "title": "FIFA 22 Nintendo Switch",
    "thumbnail": "https://ireland.apollo.olxcdn.com/v1/files/0v3bzszrrmrk1-PL/image;s=200x0;q=50",
    "url": "https://www.olx.pl/d/oferta/fifa-22-nintendo-switch-CID99-ID110oKk.html",
    "pricePLN": "60 zł\ndo negocjacji",
    "city": "Garwolin",
    "type": "BUY_NOW",
    "date": "12.10.2024 10:01",
    "timestamp": 1728727260000
  },
  {
    "localId": 951439991,
    "title": "Burnout Paradise Nintendo Switch",
    "thumbnail": "https://ireland.apollo.olxcdn.com/v1/files/sqoytjrxqswt1-PL/image;s=200x0;q=50",
    "url": "https://www.olx.pl/d/oferta/burnout-paradise-nintendo-switch-CID99-ID12o90j.html",
    "pricePLN": "100 zł",
    "city": "Ruciane",
    "type": "BUY_NOW",
    "date": "Nida",
    "timestamp": null
  },
  {
    "localId": 951438558,
    "title": "Super Mario 3D All-Stars Nintendo Switch",
    "thumbnail": "https://ireland.apollo.olxcdn.com/v1/files/5ndus3nqxi862-PL/image;s=200x0;q=50",
    "url": "https://www.olx.pl/d/oferta/super-mario-3d-all-stars-nintendo-switch-CID99-ID12o8Dc.html",
    "pricePLN": "320 zł",
    "city": "Ruciane",
    "type": "BUY_NOW",
    "date": "Nida",
    "timestamp": null
  },
  {
    "localId": 951437800,
    "title": "The Legend of Zelda Breath of The Wild Switch",
    "thumbnail": "https://ireland.apollo.olxcdn.com/v1/files/qjkh68zt2hlq-PL/image;s=200x0;q=50",
    "url": "https://www.olx.pl/d/oferta/the-legend-of-zelda-breath-of-the-wild-switch-CID99-ID12o8qY.html",
    "pricePLN": "130 zł\ndo negocjacji",
    "city": "Ruciane",
    "type": "BUY_NOW",
    "date": "Nida",
    "timestamp": null
  },
  {
    "localId": 951435453,
    "title": "Super Monkey Ball Banana Rumble switch",
    "thumbnail": "https://ireland.apollo.olxcdn.com/v1/files/qzwxzgbtwpk82-PL/image;s=200x0;q=50",
    "url": "https://www.olx.pl/d/oferta/super-monkey-ball-banana-rumble-switch-CID99-ID12o7P7.html",
    "pricePLN": "89 zł",
    "city": "Poznań, Jeżyce",
    "type": "BUY_NOW",
    "date": "12.10.2024 09:46",
    "timestamp": 1728726360000
  },
  {
    "localId": 951434745,
    "title": "Gra na nintendo switch Animal Crossing",
    "thumbnail": "https://www.olx.pl/app/static/media/no_thumbnail.c222b0530.svg",
    "url": "https://www.olx.pl/d/oferta/gra-na-nintendo-switch-animal-crossing-CID99-ID12o7DH.html",
    "pricePLN": "25 zł",
    "city": "Zalasewo",
    "type": "BUY_NOW",
    "date": "12.10.2024 09:44",
    "timestamp": 1728726240000
  },
  {
    "localId": 937417495,
    "title": "Gra SWITCH Silent Hope nowa",
    "thumbnail": "https://www.olx.pl/app/static/media/no_thumbnail.c222b0530.svg",
    "url": "https://www.olx.pl/d/oferta/gra-switch-silent-hope-nowa-CID99-ID11rj71.html",
    "pricePLN": "149,99 zł",
    "city": "Rybnik",
    "type": "BUY_NOW",
    "date": "12.10.2024 09:44",
    "timestamp": 1728726240000
  },
  {
    "localId": 944099399,
    "title": "Gra EA SPORTS FC 24 Nintendo Switch niemiecka wersja",
    "thumbnail": "https://www.olx.pl/app/static/media/no_thumbnail.c222b0530.svg",
    "url": "https://www.olx.pl/d/oferta/gra-ea-sports-fc-24-nintendo-switch-niemiecka-wersja-CID99-ID11TlnF.html",
    "pricePLN": "99,99 zł",
    "city": "Recz",
    "type": "BUY_NOW",
    "date": "12.10.2024 09:43",
    "timestamp": 1728726180000
  },
  {
    "localId": 944099409,
    "title": "Gra EA SPORTS FC 24 Nintendo Switch niemiecka wersja",
    "thumbnail": "https://www.olx.pl/app/static/media/no_thumbnail.c222b0530.svg",
    "url": "https://www.olx.pl/d/oferta/gra-ea-sports-fc-24-nintendo-switch-niemiecka-wersja-CID99-ID11TlnP.html",
    "pricePLN": "99,99 zł",
    "city": "Recz",
    "type": "BUY_NOW",
    "date": "12.10.2024 09:43",
    "timestamp": 1728726180000
  },
  {
    "localId": 944099457,
    "title": "Gra EA SPORTS FC 24 Nintendo Switch niemiecka wersja",
    "thumbnail": "https://www.olx.pl/app/static/media/no_thumbnail.c222b0530.svg",
    "url": "https://www.olx.pl/d/oferta/gra-ea-sports-fc-24-nintendo-switch-niemiecka-wersja-CID99-ID11TloB.html",
    "pricePLN": "99,99 zł",
    "city": "Recz",
    "type": "BUY_NOW",
    "date": "12.10.2024 09:43",
    "timestamp": 1728726180000
  },
  {
    "localId": 944097066,
    "title": "Gra Pokemon Scarlatto Nintendo Switch",
    "thumbnail": "https://www.olx.pl/app/static/media/no_thumbnail.c222b0530.svg",
    "url": "https://www.olx.pl/d/oferta/gra-pokemon-scarlatto-nintendo-switch-CID99-ID11TkM2.html",
    "pricePLN": "339 zł",
    "city": "Recz",
    "type": "BUY_NOW",
    "date": "12.10.2024 09:43",
    "timestamp": 1728726180000
  },
  {
    "localId": 944099446,
    "title": "Gra EA SPORTS FC 24 Nintendo Switch niemiecka wersja",
    "thumbnail": "https://www.olx.pl/app/static/media/no_thumbnail.c222b0530.svg",
    "url": "https://www.olx.pl/d/oferta/gra-ea-sports-fc-24-nintendo-switch-niemiecka-wersja-CID99-ID11Tloq.html",
    "pricePLN": "99,99 zł",
    "city": "Recz",
    "type": "BUY_NOW",
    "date": "12.10.2024 09:43",
    "timestamp": 1728726180000
  },
  {
    "localId": 944099378,
    "title": "Gra EA SPORTS FC 24 Nintendo Switch niemiecka wersja",
    "thumbnail": "https://www.olx.pl/app/static/media/no_thumbnail.c222b0530.svg",
    "url": "https://www.olx.pl/d/oferta/gra-ea-sports-fc-24-nintendo-switch-niemiecka-wersja-CID99-ID11Tlnk.html",
    "pricePLN": "99,99 zł",
    "city": "Recz",
    "type": "BUY_NOW",
    "date": "12.10.2024 09:43",
    "timestamp": 1728726180000
  },
  {
    "localId": 944343663,
    "title": "Sifu Redemption Edition Nintendo Switch, NOWY, Centrum Grania",
    "thumbnail": "https://www.olx.pl/app/static/media/no_thumbnail.c222b0530.svg",
    "url": "https://www.olx.pl/d/oferta/sifu-redemption-edition-nintendo-switch-nowy-centrum-grania-CID99-ID11UmWp.html",
    "pricePLN": "399 zł",
    "city": "Lublin",
    "type": "BUY_NOW",
    "date": "12.10.2024 09:42",
    "timestamp": 1728726120000
  },
  {
    "localId": 944341029,
    "title": "Oddword Soulstorm Collector's Oddition Nintendo Switch, Centrum Grania",
    "thumbnail": "https://www.olx.pl/app/static/media/no_thumbnail.c222b0530.svg",
    "url": "https://www.olx.pl/d/oferta/oddword-soulstorm-collectors-oddition-nintendo-switch-centrum-grania-CID99-ID11UmeW.html",
    "pricePLN": "559 zł",
    "city": "Lublin",
    "type": "BUY_NOW",
    "date": "12.10.2024 09:42",
    "timestamp": 1728726120000
  },
  {
    "localId": 951434100,
    "title": "Hogwarts legacy Nintendo switch (bez pudełka)",
    "thumbnail": "https://www.olx.pl/app/static/media/no_thumbnail.c222b0530.svg",
    "url": "https://www.olx.pl/d/oferta/hogwarts-legacy-nintendo-switch-bez-pudelka-CID99-ID12o7ti.html",
    "pricePLN": "110 zł",
    "city": "Dębica",
    "type": "BUY_NOW",
    "date": "12.10.2024 09:42",
    "timestamp": 1728726120000
  },
  {
    "localId": 937416300,
    "title": "Gra SWITCH Monster Hunter Stories 2: Wind of Ruin nowa",
    "thumbnail": "https://www.olx.pl/app/static/media/no_thumbnail.c222b0530.svg",
    "url": "https://www.olx.pl/d/oferta/gra-switch-monster-hunter-stories-2-wind-of-ruin-nowa-CID99-ID11riNK.html",
    "pricePLN": "179,99 zł",
    "city": "Rybnik",
    "type": "BUY_NOW",
    "date": "12.10.2024 09:40",
    "timestamp": 1728726000000
  },
  {
    "localId": 951433525,
    "title": "Zelda Breath of the Wild (bez pudełka)",
    "thumbnail": "https://www.olx.pl/app/static/media/no_thumbnail.c222b0530.svg",
    "url": "https://www.olx.pl/d/oferta/zelda-breath-of-the-wild-bez-pudelka-CID99-ID12o7k1.html",
    "pricePLN": "110 zł",
    "city": "Dębica",
    "type": "BUY_NOW",
    "date": "12.10.2024 09:40",
    "timestamp": 1728726000000
  },
  {
    "localId": 951433305,
    "title": "Fifa 24 nintendo",
    "thumbnail": "https://www.olx.pl/app/static/media/no_thumbnail.c222b0530.svg",
    "url": "https://www.olx.pl/d/oferta/fifa-24-nintendo-CID99-ID12o7gt.html",
    "pricePLN": "100 zł",
    "city": "Górzyn",
    "type": "BUY_NOW",
    "date": "12.10.2024 09:39",
    "timestamp": 1728725940000
  },
  {
    "localId": 951432929,
    "title": "Splatoon 2 - gra Nintendo Switch",
    "thumbnail": "https://www.olx.pl/app/static/media/no_thumbnail.c222b0530.svg",
    "url": "https://www.olx.pl/d/oferta/splatoon-2-gra-nintendo-switch-CID99-ID12o7ap.html",
    "pricePLN": "70 zł",
    "city": "Warszawa, Ursynów",
    "type": "BUY_NOW",
    "date": "12.10.2024 09:37",
    "timestamp": 1728725820000
  },
  {
    "localId": 937415208,
    "title": "Gra SWITCH Sushi Striker: The Way of Sushido nowa",
    "thumbnail": "https://www.olx.pl/app/static/media/no_thumbnail.c222b0530.svg",
    "url": "https://www.olx.pl/d/oferta/gra-switch-sushi-striker-the-way-of-sushido-nowa-CID99-ID11riv8.html",
    "pricePLN": "49,99 zł",
    "city": "Rybnik",
    "type": "BUY_NOW",
    "date": "12.10.2024 09:36",
    "timestamp": 1728725760000
  },
  {
    "localId": 951432602,
    "title": "Kirby and the forgotten land - Switch",
    "thumbnail": "https://www.olx.pl/app/static/media/no_thumbnail.c222b0530.svg",
    "url": "https://www.olx.pl/d/oferta/kirby-and-the-forgotten-land-switch-CID99-ID12o758.html",
    "pricePLN": "180 zł",
    "city": "Bydgoszcz",
    "type": "BUY_NOW",
    "date": "12.10.2024 09:36",
    "timestamp": 1728725760000
  },
  {
    "localId": 951432417,
    "title": "MarioKart 8 Deluxe gra Nintendo Switch",
    "thumbnail": "https://www.olx.pl/app/static/media/no_thumbnail.c222b0530.svg",
    "url": "https://www.olx.pl/d/oferta/mariokart-8-deluxe-gra-nintendo-switch-CID99-ID12o729.html",
    "pricePLN": "180 zł",
    "city": "Warszawa, Ursynów",
    "type": "BUY_NOW",
    "date": "12.10.2024 09:35",
    "timestamp": 1728725700000
  },
  {
    "localId": 930717408,
    "title": "Galak Z/Skulls Of The Shogun Nowa Folia Limit 1/1500 Nintendo Switch",
    "thumbnail": "https://www.olx.pl/app/static/media/no_thumbnail.c222b0530.svg",
    "url": "https://www.olx.pl/d/oferta/galak-z-skulls-of-the-shogun-nowa-folia-limit-1-1500-nintendo-switch-CID99-ID10Zc76.html",
    "pricePLN": "119,99 zł",
    "city": "Warszawa, Targówek",
    "type": "BUY_NOW",
    "date": "12.10.2024 09:34",
    "timestamp": 1728725640000
  },
  {
    "localId": 951432327,
    "title": "FC 24 - Nintendo Switch",
    "thumbnail": "https://www.olx.pl/app/static/media/no_thumbnail.c222b0530.svg",
    "url": "https://www.olx.pl/d/oferta/fc-24-nintendo-switch-CID99-ID12o70H.html",
    "pricePLN": "80 zł",
    "city": "Bydgoszcz",
    "type": "BUY_NOW",
    "date": "12.10.2024 09:34",
    "timestamp": 1728725640000
  },
  {
    "localId": 951432240,
    "title": "Kirby and the forgotten land",
    "thumbnail": "https://www.olx.pl/app/static/media/no_thumbnail.c222b0530.svg",
    "url": "https://www.olx.pl/d/oferta/kirby-and-the-forgotten-land-CID99-ID12o6Zi.html",
    "pricePLN": "150 zł\ndo negocjacji",
    "city": "Warszawa, Praga",
    "type": "BUY_NOW",
    "date": "Południe",
    "timestamp": null
  },
  {
    "localId": 951431951,
    "title": "New Pokemon Snap Switch",
    "thumbnail": "https://www.olx.pl/app/static/media/no_thumbnail.c222b0530.svg",
    "url": "https://www.olx.pl/d/oferta/new-pokemon-snap-switch-CID99-ID12o6UD.html",
    "pricePLN": "150 zł",
    "city": "Bielsko",
    "type": "BUY_NOW",
    "date": "Biała",
    "timestamp": null
  },
  {
    "localId": 951431678,
    "title": "Super Mario Odyssey - gra Nintento Switch",
    "thumbnail": "https://www.olx.pl/app/static/media/no_thumbnail.c222b0530.svg",
    "url": "https://www.olx.pl/d/oferta/super-mario-odyssey-gra-nintento-switch-CID99-ID12o6Qe.html",
    "pricePLN": "150 zł",
    "city": "Warszawa, Ursynów",
    "type": "BUY_NOW",
    "date": "12.10.2024 09:32",
    "timestamp": 1728725520000
  },
  {
    "localId": 951431674,
    "title": "Pokemon Legends Arceus Switch",
    "thumbnail": "https://www.olx.pl/app/static/media/no_thumbnail.c222b0530.svg",
    "url": "https://www.olx.pl/d/oferta/pokemon-legends-arceus-switch-CID99-ID12o6Qa.html",
    "pricePLN": "150 zł",
    "city": "Bielsko",
    "type": "BUY_NOW",
    "date": "Biała",
    "timestamp": null
  },
  {
    "localId": 937413908,
    "title": "Gra SWITCH Hello Neighbor 2 Deluxe Edition nowa",
    "thumbnail": "https://www.olx.pl/app/static/media/no_thumbnail.c222b0530.svg",
    "url": "https://www.olx.pl/d/oferta/gra-switch-hello-neighbor-2-deluxe-edition-nowa-CID99-ID11riba.html",
    "pricePLN": "119,99 zł",
    "city": "Rybnik",
    "type": "BUY_NOW",
    "date": "12.10.2024 09:31",
    "timestamp": 1728725460000
  },
  {
    "localId": 937413649,
    "title": "Gra SWITCH MotoGP20 nowa",
    "thumbnail": "https://www.olx.pl/app/static/media/no_thumbnail.c222b0530.svg",
    "url": "https://www.olx.pl/d/oferta/gra-switch-motogp20-nowa-CID99-ID11ri6Z.html",
    "pricePLN": "59,99 zł",
    "city": "Rybnik",
    "type": "BUY_NOW",
    "date": "12.10.2024 09:30",
    "timestamp": 1728725400000
  },
  {
    "localId": 944691643,
    "title": "SONIC COLOURS: Ultimate PL | Nintendo Switch",
    "thumbnail": "https://www.olx.pl/app/static/media/no_thumbnail.c222b0530.svg",
    "url": "https://www.olx.pl/d/oferta/sonic-colours-ultimate-pl-nintendo-switch-CID99-ID11WPrZ.html",
    "pricePLN": "89 zł",
    "city": "Chylice",
    "type": "BUY_NOW",
    "date": "Pólko",
    "timestamp": null
  },
  {
    "localId": 944208726,
    "title": "Nintendo gra pokemon pikachu",
    "thumbnail": "https://www.olx.pl/app/static/media/no_thumbnail.c222b0530.svg",
    "url": "https://www.olx.pl/d/oferta/nintendo-gra-pokemon-pikachu-CID99-ID11TNP0.html",
    "pricePLN": "160 zł",
    "city": "Smętowo Graniczne",
    "type": "BUY_NOW",
    "date": "12.10.2024 09:25",
    "timestamp": 1728725100000
  },
  {
    "localId": 944209691,
    "title": "Nintendo gra Mario Rabbids Sparks of hope",
    "thumbnail": "https://www.olx.pl/app/static/media/no_thumbnail.c222b0530.svg",
    "url": "https://www.olx.pl/d/oferta/nintendo-gra-mario-rabbids-sparks-of-hope-CID99-ID11TO4z.html",
    "pricePLN": "100 zł",
    "city": "Smętowo Graniczne",
    "type": "BUY_NOW",
    "date": "12.10.2024 09:24",
    "timestamp": 1728725040000
  },
  {
    "localId": 944210508,
    "title": "Nintendo gra Minecraft",
    "thumbnail": "https://www.olx.pl/app/static/media/no_thumbnail.c222b0530.svg",
    "url": "https://www.olx.pl/d/oferta/nintendo-gra-minecraft-CID99-ID11TOhK.html",
    "pricePLN": "90 zł",
    "city": "Smętowo Graniczne",
    "type": "BUY_NOW",
    "date": "12.10.2024 09:24",
    "timestamp": 1728725040000
  },
  {
    "localId": 951428659,
    "title": "Doom Nintendo Switch Tomland.eu Sklep",
    "thumbnail": "https://www.olx.pl/app/static/media/no_thumbnail.c222b0530.svg",
    "url": "https://www.olx.pl/d/oferta/doom-nintendo-switch-tomland-eu-sklep-CID99-ID12o63x.html",
    "pricePLN": "139 zł",
    "city": "Wrocław, Stare Miasto",
    "type": "BUY_NOW",
    "date": "12.10.2024 09:19",
    "timestamp": 1728724740000
  },
  {
    "localId": 938772510,
    "title": "Owlboy - Nintendo Switch PL",
    "thumbnail": "https://www.olx.pl/app/static/media/no_thumbnail.c222b0530.svg",
    "url": "https://www.olx.pl/d/oferta/owlboy-nintendo-switch-pl-CID99-ID11vZC6.html",
    "pricePLN": "120 zł",
    "city": "Kraków, Mistrzejowice",
    "type": "BUY_NOW",
    "date": "12.10.2024 09:17",
    "timestamp": 1728724620000
  },
  {
    "localId": 951426352,
    "title": "Shantae 1/2 Genie Hero Ultimate Edition Switch",
    "thumbnail": "https://www.olx.pl/app/static/media/no_thumbnail.c222b0530.svg",
    "url": "https://www.olx.pl/d/oferta/shantae-1-2-genie-hero-ultimate-edition-switch-CID99-ID12o5sk.html",
    "pricePLN": "99,99 zł",
    "city": "Kraków, Stare Miasto",
    "type": "BUY_NOW",
    "date": "12.10.2024 09:09",
    "timestamp": 1728724140000
  },
  {
    "localId": 951425996,
    "title": "NINTENDO Lets Get Fit Nowa Nintendo Switch",
    "thumbnail": "https://www.olx.pl/app/static/media/no_thumbnail.c222b0530.svg",
    "url": "https://www.olx.pl/d/oferta/nintendo-lets-get-fit-nowa-nintendo-switch-CID99-ID12o5mA.html",
    "pricePLN": "98 zł",
    "city": "Poznań, Jeżyce",
    "type": "BUY_NOW",
    "date": "12.10.2024 09:07",
    "timestamp": 1728724020000
  },
  {
    "localId": 951425656,
    "title": "Carrion Nintendo Switch",
    "thumbnail": "https://www.olx.pl/app/static/media/no_thumbnail.c222b0530.svg",
    "url": "https://www.olx.pl/d/oferta/carrion-nintendo-switch-CID99-ID12o5h6.html",
    "pricePLN": "149,99 zł",
    "city": "Kraków, Stare Miasto",
    "type": "BUY_NOW",
    "date": "12.10.2024 09:06",
    "timestamp": 1728723960000
  }
]